[{"code_insee":"69001","nom":"Affoux","codes_postaux":["69170"],"code_dep":"69","code_region":"84","population":398,"surface_km2":10.64,"lat":45.8448,"lon":4.4116,"fibre_pct":95.0,"securite":{"taux_pour_mille":0.0,"annee":2024},"socio":{"annee":2021,"revenu_median":24970.0},"vivrescore":87},{"code_insee":"69002","nom":"Aigueperse","codes_postaux":["69790"],"code_dep":"69","code_region":"84","population":235,"surface_km2":12.94,"lat":46.2822,"lon":4.4268,"fibre_pct":92.5,"securite":{"taux_pour_mille":0.0,"annee":2024},"socio":{"annee":2021,"revenu_median":21290.0},"vivrescore":80},{"code_insee":"69003","nom":"Albigny-sur-Saône","codes_postaux":["69250"],"code_dep":"69","code_region":"84","population":3057,"surface_km2":2.62,"lat":45.8666,"lon":4.8284,"fibre_pct":97.0,"securite":{"taux_pour_mille":46.1,"annee":2024},"socio":{"annee":2021,"taux_pauvrete":11.0,"revenu_median":27080.0},"vivrescore":67},{"code_insee":"69004","nom":"Alix","codes_postaux":["69380"],"code_dep":"69","code_region":"84","population":777,"surface_km2":3.61,"lat":45.9162,"lon":4.6534,"fibre_pct":88.9,"securite":{"taux_pour_mille":0.0,"annee":2024},"socio":{"annee":2021,"revenu_median":26980.0},"vivrescore":87},{"code_insee":"69005","nom":"Ambérieux","codes_postaux":["69480"],"code_dep":"69","code_region":"84","population":651,"surface_km2":4.61,"lat":45.9264,"lon":4.7427,"fibre_pct":100.0,"securite":{"taux_pour_mille":15.9,"annee":2024},"socio":{"annee":2021,"revenu_median":25550.0},"vivrescore":80},{"code_insee":"69006","nom":"Amplepuis","codes_postaux":["69550"],"code_dep":"69","code_region":"84","population":4876,"surface_km2":38.77,"lat":45.966,"lon":4.317,"fibre_pct":92.0,"securite":{"taux_pour_mille":35.4,"annee":2024},"socio":{"annee":2021,"revenu_median":21120.0,"taux_pauvrete":16.0},"vivrescore":60},{"code_insee":"69007","nom":"Ampuis","codes_postaux":["69420"],"code_dep":"69","code_region":"84","population":2769,"surface_km2":15.57,"lat":45.5034,"lon":4.8079,"fibre_pct":92.6,"securite":{"taux_pour_mille":30.1,"annee":2024},"socio":{"annee":2021,"revenu_median":26440.0},"vivrescore":67},{"code_insee":"69008","nom":"Ancy","codes_postaux":["69490"],"code_dep":"69","code_region":"84","population":671,"surface_km2":11.84,"lat":45.8362,"lon":4.5098,"fibre_pct":94.1,"securite":{"taux_pour_mille":0.0,"annee":2024},"socio":{"annee":2021,"revenu_median":25170.0},"vivrescore":87},{"code_insee":"69009","nom":"Anse","codes_postaux":["69480"],"code_dep":"69","code_region":"84","population":8206,"surface_km2":15.28,"lat":45.9451,"lon":4.7049,"fibre_pct":97.4,"securite":{"taux_pour_mille":50.0,"annee":2024},"socio":{"annee":2021,"taux_pauvrete":10.0,"revenu_median":24690.0},"vivrescore":60},{"code_insee":"69010","nom":"L'Arbresle","codes_postaux":["69210"],"code_dep":"69","code_region":"84","population":6537,"surface_km2":3.36,"lat":45.8347,"lon":4.6102,"fibre_pct":97.8,"securite":{"taux_pour_mille":40.5,"annee":2024},"socio":{"annee":2021,"revenu_median":23450.0,"taux_pauvrete":12.0},"vivrescore":60},{"code_insee":"69012","nom":"Les Ardillats","codes_postaux":["69430"],"code_dep":"69","code_region":"84","population":628,"surface_km2":22.95,"lat":46.1885,"lon":4.5293,"fibre_pct":80.4,"securite":{"taux_pour_mille":0.0,"annee":2024},"socio":{"annee":2021,"revenu_median":24030.0},"vivrescore":80},{"code_insee":"69013","nom":"Arnas","codes_postaux":["69400"],"code_dep":"69","code_region":"84","population":4601,"surface_km2":17.85,"lat":46.0194,"lon":4.7102,"fibre_pct":99.7,"securite":{"taux_pour_mille":41.5,"annee":2024},"socio":{"annee":2021,"taux_pauvrete":9.0,"revenu_median":24910.0},"vivrescore":60},{"code_insee":"69014","nom":"Aveize","codes_postaux":["69610"],"code_dep":"69","code_region":"84","population":1110,"surface_km2":16.87,"lat":45.6799,"lon":4.4744,"fibre_pct":85.9,"securite":{"taux_pour_mille":0.0,"annee":2024},"socio":{"annee":2021,"revenu_median":22620.0},"vivrescore":80},{"code_insee":"69016","nom":"Azolette","codes_postaux":["69790"],"code_dep":"69","code_region":"84","population":120,"surface_km2":4.26,"lat":46.1917,"lon":4.4146,"fibre_pct":46.2,"securite":{"taux_pour_mille":0.0,"annee":2024},"socio":{"annee":2021,"revenu_median":23200.0},"vivrescore":67},{"code_insee":"69017","nom":"Bagnols","codes_postaux":["69620"],"code_dep":"69","code_region":"84","population":765,"surface_km2":7.46,"lat":45.9104,"lon":4.6205,"fibre_pct":100.0,"securite":{"taux_pour_mille":0.0,"annee":2024},"socio":{"annee":2021,"revenu_median":26690.0},"vivrescore":93},{"code_insee":"69018","nom":"Beaujeu","codes_postaux":["69430"],"code_dep":"69","code_region":"84","population":2082,"surface_km2":17.74,"lat":46.1585,"lon":4.5802,"fibre_pct":93.0,"securite":{"taux_pour_mille":21.9,"annee":2024},"socio":{"annee":2021,"revenu_median":21680.0},"vivrescore":67},{"code_insee":"69019","nom":"Belleville-en-Beaujolais","codes_postaux":["69220"],"code_dep":"69","code_region":"84","population":14016,"surface_km2":22.82,"lat":46.1145,"lon":4.7291,"fibre_pct":99.6,"securite":{"taux_pour_mille":42.7,"annee":2024},"socio":{"annee":2021,"revenu_median":22210.0,"taux_pauvrete":13.0},"vivrescore":60},{"code_insee":"69020","nom":"Belmont-d'Azergues","codes_postaux":["69380"],"code_dep":"69","code_region":"84","population":720,"surface_km2":1.56,"lat":45.8673,"lon":4.6685,"fibre_pct":100.0,"securite":{"taux_pour_mille":0.0,"annee":2024},"socio":{"annee":2021,"revenu_median":29010.0},"vivrescore":93},{"code_insee":"69021","nom":"Bessenay","codes_postaux":["69690"],"code_dep":"69","code_region":"84","population":2331,"surface_km2":13.99,"lat":45.7712,"lon":4.5484,"fibre_pct":98.8,"securite":{"taux_pour_mille":7.7,"annee":2024},"socio":{"annee":2021,"revenu_median":24500.0},"vivrescore":80},{"code_insee":"69022","nom":"Bibost","codes_postaux":["69690"],"code_dep":"69","code_region":"84","population":538,"surface_km2":5.35,"lat":45.7976,"lon":4.5494,"fibre_pct":99.6,"securite":{"taux_pour_mille":0.0,"annee":2024},"socio":{"annee":2021,"revenu_median":24520.0},"vivrescore":87},{"code_insee":"69023","nom":"Blacé","codes_postaux":["69460"],"code_dep":"69","code_region":"84","population":1715,"surface_km2":11.0,"lat":46.0364,"lon":4.6308,"fibre_pct":99.8,"securite":{"taux_pour_mille":4.7,"annee":2024},"socio":{"annee":2021,"revenu_median":27320.0},"vivrescore":93},{"code_insee":"69024","nom":"Val d'Oingt","codes_postaux":["69620"],"code_dep":"69","code_region":"84","population":4117,"surface_km2":18.28,"lat":45.9386,"lon":4.5668,"fibre_pct":94.3,"securite":{"taux_pour_mille":22.9,"annee":2024},"socio":{"annee":2021,"taux_pauvrete":5.0,"revenu_median":26650.0},"vivrescore":73},{"code_insee":"69026","nom":"Le Breuil","codes_postaux":["69620"],"code_dep":"69","code_region":"84","population":533,"surface_km2":5.66,"lat":45.8909,"lon":4.5889,"fibre_pct":99.6,"securite":{"taux_pour_mille":0.0,"annee":2024},"socio":{"annee":2021,"revenu_median":26280.0},"vivrescore":93},{"code_insee":"69027","nom":"Brignais","codes_postaux":["69530"],"code_dep":"69","code_region":"84","population":12503,"surface_km2":10.31,"lat":45.6751,"lon":4.7527,"fibre_pct":98.8,"securite":{"taux_pour_mille":51.3,"annee":2024},"socio":{"annee":2021,"revenu_median":26720.0,"taux_pauvrete":10.0},"vivrescore":67},{"code_insee":"69028","nom":"Brindas","codes_postaux":["69126"],"code_dep":"69","code_region":"84","population":6775,"surface_km2":11.4,"lat":45.7183,"lon":4.703,"fibre_pct":94.1,"securite":{"taux_pour_mille":27.5,"annee":2024},"socio":{"annee":2021,"revenu_median":29700.0,"taux_pauvrete":5.0},"vivrescore":67},{"code_insee":"69029","nom":"Bron","codes_postaux":["69500"],"code_dep":"69","code_region":"84","population":42982,"surface_km2":10.3,"lat":45.7355,"lon":4.9116,"fibre_pct":97.0,"securite":{"taux_pour_mille":67.3,"annee":2024},"socio":{"annee":2021,"taux_pauvrete":21.0,"revenu_median":21950.0},"vivrescore":60},{"code_insee":"69030","nom":"Brullioles","codes_postaux":["69690"],"code_dep":"69","code_region":"84","population":821,"surface_km2":12.53,"lat":45.7617,"lon":4.49,"fibre_pct":95.6,"securite":{"taux_pour_mille":0.0,"annee":2024},"socio":{"annee":2021,"revenu_median":24700.0},"vivrescore":87},{"code_insee":"69031","nom":"Brussieu","codes_postaux":["69690"],"code_dep":"69","code_region":"84","population":1382,"surface_km2":6.82,"lat":45.745,"lon":4.5201,"fibre_pct":93.0,"securite":{"taux_pour_mille":8.0,"annee":2024},"socio":{"annee":2021,"revenu_median":25730.0},"vivrescore":80},{"code_insee":"69032","nom":"Bully","codes_postaux":["69210"],"code_dep":"69","code_region":"84","population":2213,"surface_km2":12.78,"lat":45.8595,"lon":4.5786,"fibre_pct":100.0,"securite":{"taux_pour_mille":22.4,"annee":2024},"socio":{"annee":2021,"revenu_median":27450.0},"vivrescore":80},{"code_insee":"69033","nom":"Cailloux-sur-Fontaines","codes_postaux":["69270"],"code_dep":"69","code_region":"84","population":2989,"surface_km2":8.46,"lat":45.8592,"lon":4.8817,"fibre_pct":98.3,"securite":{"taux_pour_mille":17.6,"annee":2024},"socio":{"annee":2021,"revenu_median":34010.0},"vivrescore":87},{"code_insee":"69034","nom":"Caluire-et-Cuire","codes_postaux":["69300"],"code_dep":"69","code_region":"84","population":43597,"surface_km2":10.44,"lat":45.7986,"lon":4.8494,"fibre_pct":95.0,"securite":{"taux_pour_mille":48.4,"annee":2024},"socio":{"annee":2021,"taux_pauvrete":11.0,"revenu_median":27370.0},"vivrescore":67},{"code_insee":"69035","nom":"Cenves","codes_postaux":["69840"],"code_dep":"69","code_region":"84","population":409,"surface_km2":26.42,"lat":46.2801,"lon":4.6632,"fibre_pct":53.4,"securite":{"taux_pour_mille":0.0,"annee":2024},"socio":{"annee":2021,"revenu_median":24870.0},"vivrescore":67},{"code_insee":"69036","nom":"Cercié","codes_postaux":["69220"],"code_dep":"69","code_region":"84","population":1131,"surface_km2":4.99,"lat":46.1251,"lon":4.6702,"fibre_pct":99.0,"securite":{"taux_pour_mille":8.8,"annee":2024},"socio":{"annee":2021,"revenu_median":24520.0},"vivrescore":80},{"code_insee":"69037","nom":"Chambost-Allières","codes_postaux":["69870"],"code_dep":"69","code_region":"84","population":816,"surface_km2":13.95,"lat":46.017,"lon":4.509,"fibre_pct":90.6,"securite":{"taux_pour_mille":0.0,"annee":2024},"socio":{"annee":2021,"revenu_median":23330.0},"vivrescore":80},{"code_insee":"69038","nom":"Chambost-Longessaigne","codes_postaux":["69770"],"code_dep":"69","code_region":"84","population":930,"surface_km2":15.42,"lat":45.778,"lon":4.3784,"fibre_pct":91.7,"securite":{"taux_pour_mille":16.3,"annee":2024},"socio":{"annee":2021,"revenu_median":21860.0},"vivrescore":67},{"code_insee":"69039","nom":"Chamelet","codes_postaux":["69620"],"code_dep":"69","code_region":"84","population":706,"surface_km2":14.76,"lat":45.9829,"lon":4.4973,"fibre_pct":89.0,"securite":{"taux_pour_mille":0.0,"annee":2024},"socio":{"annee":2021,"revenu_median":24090.0},"vivrescore":80},{"code_insee":"69040","nom":"Champagne-au-Mont-d'Or","codes_postaux":["69410"],"code_dep":"69","code_region":"84","population":6311,"surface_km2":2.57,"lat":45.8006,"lon":4.7864,"fibre_pct":96.7,"securite":{"taux_pour_mille":66.9,"annee":2024},"socio":{"annee":2021,"revenu_median":27100.0,"taux_pauvrete":11.0},"vivrescore":67},{"code_insee":"69042","nom":"La Chapelle-sur-Coise","codes_postaux":["69590"],"code_dep":"69","code_region":"84","population":565,"surface_km2":6.61,"lat":45.6513,"lon":4.4959,"fibre_pct":96.5,"securite":{"taux_pour_mille":0.0,"annee":2024},"socio":{"annee":2021,"revenu_median":25080.0},"vivrescore":93},{"code_insee":"69043","nom":"Chaponost","codes_postaux":["69630"],"code_dep":"69","code_region":"84","population":9382,"surface_km2":16.26,"lat":45.7089,"lon":4.7452,"fibre_pct":99.9,"securite":{"taux_pour_mille":38.1,"annee":2024},"socio":{"annee":2021,"taux_pauvrete":6.0,"revenu_median":31090.0},"vivrescore":80},{"code_insee":"69044","nom":"Charbonnières-les-Bains","codes_postaux":["69260"],"code_dep":"69","code_region":"84","population":5383,"surface_km2":4.11,"lat":45.7792,"lon":4.743,"fibre_pct":95.5,"securite":{"taux_pour_mille":59.0,"annee":2024},"socio":{"annee":2021,"revenu_median":36390.0,"taux_pauvrete":5.0},"vivrescore":73},{"code_insee":"69045","nom":"Charentay","codes_postaux":["69220"],"code_dep":"69","code_region":"84","population":1273,"surface_km2":13.97,"lat":46.0814,"lon":4.6926,"fibre_pct":98.2,"securite":{"taux_pour_mille":0.0,"annee":2024},"socio":{"annee":2021,"revenu_median":26070.0},"vivrescore":93},{"code_insee":"69046","nom":"Charly","codes_postaux":["69390"],"code_dep":"69","code_region":"84","population":4811,"surface_km2":5.17,"lat":45.6527,"lon":4.7871,"fibre_pct":98.8,"securite":{"taux_pour_mille":34.9,"annee":2024},"socio":{"annee":2021,"revenu_median":33860.0},"vivrescore":80},{"code_insee":"69047","nom":"Charnay","codes_postaux":["69380"],"code_dep":"69","code_region":"84","population":1023,"surface_km2":7.22,"lat":45.8876,"lon":4.6602,"fibre_pct":98.5,"securite":{"taux_pour_mille":0.0,"annee":2024},"socio":{"annee":2021,"revenu_median":32860.0},"vivrescore":100},{"code_insee":"69049","nom":"Chasselay","codes_postaux":["69380"],"code_dep":"69","code_region":"84","population":2973,"surface_km2":12.89,"lat":45.8733,"lon":4.7699,"fibre_pct":99.6,"securite":{"taux_pour_mille":16.9,"annee":2024},"socio":{"annee":2021,"revenu_median":32350.0},"vivrescore":87},{"code_insee":"69050","nom":"Châtillon","codes_postaux":["69380"],"code_dep":"69","code_region":"84","population":2252,"surface_km2":10.78,"lat":45.872,"lon":4.6487,"fibre_pct":98.7,"securite":{"taux_pour_mille":15.1,"annee":2024},"socio":{"annee":2021,"revenu_median":28030.0},"vivrescore":80},{"code_insee":"69051","nom":"Chaussan","codes_postaux":["69440"],"code_dep":"69","code_region":"84","population":1218,"surface_km2":7.97,"lat":45.6387,"lon":4.6332,"fibre_pct":100.0,"securite":{"taux_pour_mille":0.0,"annee":2024},"socio":{"annee":2021,"revenu_median":27050.0},"vivrescore":93},{"code_insee":"69052","nom":"Chazay-d'Azergues","codes_postaux":["69380"],"code_dep":"69","code_region":"84","population":4410,"surface_km2":5.97,"lat":45.8743,"lon":4.71,"fibre_pct":99.5,"securite":{"taux_pour_mille":24.8,"annee":2024},"socio":{"annee":2021,"revenu_median":31020.0},"vivrescore":87},{"code_insee":"69053","nom":"Chénas","codes_postaux":["69840"],"code_dep":"69","code_region":"84","population":533,"surface_km2":8.17,"lat":46.2142,"lon":4.7069,"fibre_pct":95.2,"securite":{"taux_pour_mille":0.0,"annee":2024},"socio":{"annee":2021,"revenu_median":25220.0},"vivrescore":93},{"code_insee":"69054","nom":"Chénelette","codes_postaux":["69430"],"code_dep":"69","code_region":"84","population":369,"surface_km2":11.03,"lat":46.1707,"lon":4.4895,"fibre_pct":95.1,"securite":{"taux_pour_mille":0.0,"annee":2024},"socio":{"annee":2021,"revenu_median":24480.0},"vivrescore":87},{"code_insee":"69055","nom":"Les Chères","codes_postaux":["69380"],"code_dep":"69","code_region":"84","population":1503,"surface_km2":5.57,"lat":45.8948,"lon":4.7454,"fibre_pct":97.9,"securite":{"taux_pour_mille":18.0,"annee":2024},"socio":{"annee":2021,"revenu_median":27560.0},"vivrescore":80},{"code_insee":"69056","nom":"Chessy","codes_postaux":["69380"],"code_dep":"69","code_region":"84","population":2055,"surface_km2":4.55,"lat":45.8914,"lon":4.6168,"fibre_pct":99.3,"securite":{"taux_pour_mille":8.3,"annee":2024},"socio":{"annee":2021,"revenu_median":27050.0},"vivrescore":87},{"code_insee":"69057","nom":"Chevinay","codes_postaux":["69210"],"code_dep":"69","code_region":"84","population":580,"surface_km2":8.78,"lat":45.7767,"lon":4.5988,"fibre_pct":100.0,"securite":{"taux_pour_mille":0.0,"annee":2024},"socio":{"annee":2021,"revenu_median":26530.0},"vivrescore":93},{"code_insee":"69058","nom":"Chiroubles","codes_postaux":["69115"],"code_dep":"69","code_region":"84","population":434,"surface_km2":7.29,"lat":46.1853,"lon":4.6495,"fibre_pct":90.9,"securite":{"taux_pour_mille":0.0,"annee":2024},"socio":{"annee":2021,"revenu_median":23730.0},"vivrescore":80},{"code_insee":"69059","nom":"Civrieux-d'Azergues","codes_postaux":["69380"],"code_dep":"69","code_region":"84","population":1675,"surface_km2":4.97,"lat":45.8573,"lon":4.7121,"fibre_pct":99.3,"securite":{"taux_pour_mille":23.9,"annee":2024},"socio":{"annee":2021,"revenu_median":28930.0},"vivrescore":80},{"code_insee":"69060","nom":"Claveisolles","codes_postaux":["69870"],"code_dep":"69","code_region":"84","population":577,"surface_km2":28.13,"lat":46.0966,"lon":4.5095,"fibre_pct":90.4,"securite":{"taux_pour_mille":0.0,"annee":2024},"socio":{"annee":2021,"revenu_median":21860.0},"vivrescore":80},{"code_insee":"69061","nom":"Cogny","codes_postaux":["69640"],"code_dep":"69","code_region":"84","population":1211,"surface_km2":5.86,"lat":45.9885,"lon":4.6012,"fibre_pct":99.8,"securite":{"taux_pour_mille":0.0,"annee":2024},"socio":{"annee":2021,"revenu_median":28860.0},"vivrescore":93},{"code_insee":"69062","nom":"Coise","codes_postaux":["69590"],"code_dep":"69","code_region":"84","population":800,"surface_km2":9.1,"lat":45.6133,"lon":4.4665,"fibre_pct":88.7,"securite":{"taux_pour_mille":0.0,"annee":2024},"socio":{"annee":2021,"revenu_median":22830.0},"vivrescore":80},{"code_insee":"69063","nom":"Collonges-au-Mont-d'Or","codes_postaux":["69660"],"code_dep":"69","code_region":"84","population":4669,"surface_km2":3.78,"lat":45.8188,"lon":4.8425,"fibre_pct":95.3,"securite":{"taux_pour_mille":43.7,"annee":2024},"socio":{"annee":2021,"taux_pauvrete":6.0,"revenu_median":35240.0},"vivrescore":73},{"code_insee":"69064","nom":"Condrieu","codes_postaux":["69420"],"code_dep":"69","code_region":"84","population":3957,"surface_km2":9.24,"lat":45.4748,"lon":4.7516,"fibre_pct":98.4,"securite":{"taux_pour_mille":45.4,"annee":2024},"socio":{"annee":2021,"taux_pauvrete":12.0,"revenu_median":23490.0},"vivrescore":60},{"code_insee":"69065","nom":"Corcelles-en-Beaujolais","codes_postaux":["69220"],"code_dep":"69","code_region":"84","population":1001,"surface_km2":9.34,"lat":46.1538,"lon":4.7254,"fibre_pct":99.8,"securite":{"taux_pour_mille":7.0,"annee":2024},"socio":{"annee":2021,"revenu_median":25170.0},"vivrescore":87},{"code_insee":"69066","nom":"Cours","codes_postaux":["69470"],"code_dep":"69","code_region":"84","population":4306,"surface_km2":33.8,"lat":46.0968,"lon":4.3445,"fibre_pct":96.8,"securite":{"taux_pour_mille":36.5,"annee":2024},"socio":{"annee":2021,"taux_pauvrete":16.0,"revenu_median":21050.0},"vivrescore":67},{"code_insee":"69067","nom":"Courzieu","codes_postaux":["69690"],"code_dep":"69","code_region":"84","population":1183,"surface_km2":26.86,"lat":45.7451,"lon":4.5695,"fibre_pct":100.0,"securite":{"taux_pour_mille":12.7,"annee":2024},"socio":{"annee":2021,"revenu_median":22530.0},"vivrescore":80},{"code_insee":"69068","nom":"Couzon-au-Mont-d'Or","codes_postaux":["69270"],"code_dep":"69","code_region":"84","population":2619,"surface_km2":3.13,"lat":45.8479,"lon":4.8214,"fibre_pct":94.7,"securite":{"taux_pour_mille":28.3,"annee":2024},"socio":{"annee":2021,"taux_pauvrete":9.0,"revenu_median":28290.0},"vivrescore":67},{"code_insee":"69069","nom":"Craponne","codes_postaux":["69290"],"code_dep":"69","code_region":"84","population":12084,"surface_km2":4.71,"lat":45.7456,"lon":4.7294,"fibre_pct":91.8,"securite":{"taux_pour_mille":40.8,"annee":2024},"socio":{"annee":2021,"taux_pauvrete":8.0,"revenu_median":27380.0},"vivrescore":60},{"code_insee":"69070","nom":"Cublize","codes_postaux":["69550"],"code_dep":"69","code_region":"84","population":1360,"surface_km2":15.67,"lat":46.0244,"lon":4.3921,"fibre_pct":92.6,"securite":{"taux_pour_mille":6.6,"annee":2024},"socio":{"annee":2021,"revenu_median":22890.0},"vivrescore":73},{"code_insee":"69071","nom":"Curis-au-Mont-d'Or","codes_postaux":["69250"],"code_dep":"69","code_region":"84","population":1195,"surface_km2":3.08,"lat":45.8682,"lon":4.8201,"fibre_pct":83.2,"securite":{"taux_pour_mille":0.0,"annee":2024},"socio":{"annee":2021,"revenu_median":33160.0},"vivrescore":93},{"code_insee":"69072","nom":"Dardilly","codes_postaux":["69570"],"code_dep":"69","code_region":"84","population":9221,"surface_km2":14.07,"lat":45.8133,"lon":4.7466,"fibre_pct":96.1,"securite":{"taux_pour_mille":71.9,"annee":2024},"socio":{"annee":2021,"taux_pauvrete":7.0,"revenu_median":32510.0},"vivrescore":73},{"code_insee":"69074","nom":"Denicé","codes_postaux":["69640"],"code_dep":"69","code_region":"84","population":1571,"surface_km2":9.45,"lat":46.0051,"lon":4.6503,"fibre_pct":99.2,"securite":{"taux_pour_mille":8.9,"annee":2024},"socio":{"annee":2021,"revenu_median":28360.0},"vivrescore":87},{"code_insee":"69075","nom":"Dième","codes_postaux":["69170"],"code_dep":"69","code_region":"84","population":199,"surface_km2":8.95,"lat":45.9615,"lon":4.4584,"fibre_pct":96.5,"securite":{"taux_pour_mille":0.0,"annee":2024},"socio":{"annee":2021,"revenu_median":23960.0},"vivrescore":87},{"code_insee":"69076","nom":"Dommartin","codes_postaux":["69380"],"code_dep":"69","code_region":"84","population":2687,"surface_km2":7.24,"lat":45.8372,"lon":4.7122,"fibre_pct":99.5,"securite":{"taux_pour_mille":16.5,"annee":2024},"socio":{"annee":2021,"revenu_median":34020.0},"vivrescore":87},{"code_insee":"69077","nom":"Dracé","codes_postaux":["69220"],"code_dep":"69","code_region":"84","population":1212,"surface_km2":14.88,"lat":46.154,"lon":4.773,"fibre_pct":99.1,"securite":{"taux_pour_mille":65.4,"annee":2024},"socio":{"annee":2021,"revenu_median":24320.0},"vivrescore":60},{"code_insee":"69078","nom":"Duerne","codes_postaux":["69850"],"code_dep":"69","code_region":"84","population":841,"surface_km2":11.34,"lat":45.677,"lon":4.5273,"fibre_pct":93.0,"securite":{"taux_pour_mille":0.0,"annee":2024},"socio":{"annee":2021,"revenu_median":24160.0},"vivrescore":80},{"code_insee":"69080","nom":"Échalas","codes_postaux":["69700"],"code_dep":"69","code_region":"84","population":1994,"surface_km2":20.99,"lat":45.5501,"lon":4.7294,"fibre_pct":98.1,"securite":{"taux_pour_mille":4.1,"annee":2024},"socio":{"annee":2021,"revenu_median":26910.0},"vivrescore":93},{"code_insee":"69081","nom":"Écully","codes_postaux":["69130"],"code_dep":"69","code_region":"84","population":17944,"surface_km2":8.48,"lat":45.7822,"lon":4.7737,"fibre_pct":98.9,"securite":{"taux_pour_mille":49.9,"annee":2024},"socio":{"annee":2021,"taux_pauvrete":12.0,"revenu_median":29600.0},"vivrescore":67},{"code_insee":"69082","nom":"Émeringes","codes_postaux":["69840"],"code_dep":"69","code_region":"84","population":275,"surface_km2":3.0,"lat":46.224,"lon":4.6754,"fibre_pct":99.0,"securite":{"taux_pour_mille":0.0,"annee":2024},"socio":{"annee":2021,"revenu_median":25840.0},"vivrescore":93},{"code_insee":"69083","nom":"Éveux","codes_postaux":["69210"],"code_dep":"69","code_region":"84","population":1160,"surface_km2":3.38,"lat":45.8256,"lon":4.6223,"fibre_pct":100.0,"securite":{"taux_pour_mille":0.0,"annee":2024},"socio":{"annee":2021,"revenu_median":30290.0},"vivrescore":100},{"code_insee":"69084","nom":"Fleurie","codes_postaux":["69820"],"code_dep":"69","code_region":"84","population":1382,"surface_km2":13.95,"lat":46.1953,"lon":4.6942,"fibre_pct":98.4,"securite":{"taux_pour_mille":3.7,"annee":2024},"socio":{"annee":2021,"revenu_median":24350.0},"vivrescore":87},{"code_insee":"69085","nom":"Fleurieu-sur-Saône","codes_postaux":["69250"],"code_dep":"69","code_region":"84","population":1597,"surface_km2":2.95,"lat":45.8582,"lon":4.8566,"fibre_pct":94.9,"securite":{"taux_pour_mille":18.1,"annee":2024},"socio":{"annee":2021,"revenu_median":31110.0},"vivrescore":80},{"code_insee":"69086","nom":"Fleurieux-sur-l'Arbresle","codes_postaux":["69210"],"code_dep":"69","code_region":"84","population":2361,"surface_km2":9.54,"lat":45.8406,"lon":4.6484,"fibre_pct":99.0,"securite":{"taux_pour_mille":13.5,"annee":2024},"socio":{"annee":2021,"revenu_median":29780.0},"vivrescore":87},{"code_insee":"69087","nom":"Fontaines-Saint-Martin","codes_postaux":["69270"],"code_dep":"69","code_region":"84","population":3098,"surface_km2":2.73,"lat":45.8445,"lon":4.8521,"fibre_pct":95.8,"securite":{"taux_pour_mille":21.2,"annee":2024},"socio":{"annee":2021,"revenu_median":34190.0},"vivrescore":87},{"code_insee":"69088","nom":"Fontaines-sur-Saône","codes_postaux":["69270"],"code_dep":"69","code_region":"84","population":6957,"surface_km2":2.34,"lat":45.8268,"lon":4.8537,"fibre_pct":98.0,"securite":{"taux_pour_mille":47.5,"annee":2024},"socio":{"annee":2021,"revenu_median":25230.0,"taux_pauvrete":11.0},"vivrescore":67},{"code_insee":"69089","nom":"Francheville","codes_postaux":["69340"],"code_dep":"69","code_region":"84","population":15604,"surface_km2":8.25,"lat":45.7386,"lon":4.7537,"fibre_pct":98.9,"securite":{"taux_pour_mille":43.4,"annee":2024},"socio":{"annee":2021,"revenu_median":28120.0,"taux_pauvrete":8.0},"vivrescore":67},{"code_insee":"69090","nom":"Frontenas","codes_postaux":["69620"],"code_dep":"69","code_region":"84","population":915,"surface_km2":3.49,"lat":45.9186,"lon":4.632,"fibre_pct":98.8,"securite":{"taux_pour_mille":0.0,"annee":2024},"socio":{"annee":2021,"revenu_median":27540.0},"vivrescore":93},{"code_insee":"69091","nom":"Givors","codes_postaux":["69700"],"code_dep":"69","code_region":"84","population":21379,"surface_km2":17.45,"lat":45.5845,"lon":4.7561,"fibre_pct":94.6,"securite":{"taux_pour_mille":93.9,"annee":2024},"socio":{"annee":2021,"revenu_median":18160.0,"taux_pauvrete":30.0},"vivrescore":47},{"code_insee":"69092","nom":"Gleizé","codes_postaux":["69400"],"code_dep":"69","code_region":"84","population":8035,"surface_km2":10.53,"lat":45.9915,"lon":4.6883,"fibre_pct":97.6,"securite":{"taux_pour_mille":46.3,"annee":2024},"socio":{"annee":2021,"taux_pauvrete":14.0,"revenu_median":23660.0},"vivrescore":60},{"code_insee":"69093","nom":"Grandris","codes_postaux":["69870"],"code_dep":"69","code_region":"84","population":1226,"surface_km2":15.15,"lat":46.034,"lon":4.4599,"fibre_pct":97.8,"securite":{"taux_pour_mille":9.1,"annee":2024},"socio":{"annee":2021,"revenu_median":21580.0},"vivrescore":80},{"code_insee":"69094","nom":"Grézieu-la-Varenne","codes_postaux":["69290"],"code_dep":"69","code_region":"84","population":6472,"surface_km2":7.49,"lat":45.7469,"lon":4.6799,"fibre_pct":91.2,"securite":{"taux_pour_mille":33.7,"annee":2024},"socio":{"annee":2021,"taux_pauvrete":7.0,"revenu_median":27230.0},"vivrescore":67},{"code_insee":"69095","nom":"Grézieu-le-Marché","codes_postaux":["69610"],"code_dep":"69","code_region":"84","population":834,"surface_km2":11.52,"lat":45.661,"lon":4.4243,"fibre_pct":91.6,"securite":{"taux_pour_mille":0.0,"annee":2024},"socio":{"annee":2021,"revenu_median":22700.0},"vivrescore":80},{"code_insee":"69096","nom":"Grigny-sur-Rhône","codes_postaux":["69520"],"code_dep":"69","code_region":"84","population":10030,"surface_km2":5.9,"lat":45.6104,"lon":4.7858,"fibre_pct":95.0,"securite":{"taux_pour_mille":46.1,"annee":2024},"socio":{"annee":2021,"taux_pauvrete":17.0,"revenu_median":21900.0},"vivrescore":60},{"code_insee":"69097","nom":"Les Haies","codes_postaux":["69420"],"code_dep":"69","code_region":"84","population":723,"surface_km2":15.91,"lat":45.5122,"lon":4.7401,"fibre_pct":93.2,"securite":{"taux_pour_mille":0.0,"annee":2024},"socio":{"annee":2021,"revenu_median":25590.0},"vivrescore":87},{"code_insee":"69098","nom":"Les Halles","codes_postaux":["69610"],"code_dep":"69","code_region":"84","population":472,"surface_km2":3.1,"lat":45.7175,"lon":4.4345,"fibre_pct":98.0,"securite":{"taux_pour_mille":10.4,"annee":2024},"socio":{"annee":2021,"revenu_median":22970.0},"vivrescore":80},{"code_insee":"69099","nom":"Haute-Rivoire","codes_postaux":["69610"],"code_dep":"69","code_region":"84","population":1430,"surface_km2":20.64,"lat":45.7172,"lon":4.4053,"fibre_pct":91.0,"securite":{"taux_pour_mille":0.0,"annee":2024},"socio":{"annee":2021,"revenu_median":22560.0},"vivrescore":80},{"code_insee":"69100","nom":"Irigny","codes_postaux":["69540"],"code_dep":"69","code_region":"84","population":9034,"surface_km2":8.91,"lat":45.6747,"lon":4.8143,"fibre_pct":95.4,"securite":{"taux_pour_mille":48.0,"annee":2024},"socio":{"annee":2021,"revenu_median":25740.0,"taux_pauvrete":12.0},"vivrescore":67},{"code_insee":"69102","nom":"Joux","codes_postaux":["69170"],"code_dep":"69","code_region":"84","population":752,"surface_km2":25.05,"lat":45.8895,"lon":4.368,"fibre_pct":83.8,"securite":{"taux_pour_mille":0.0,"annee":2024},"socio":{"annee":2021,"revenu_median":23230.0},"vivrescore":80},{"code_insee":"69103","nom":"Juliénas","codes_postaux":["69840"],"code_dep":"69","code_region":"84","population":880,"surface_km2":7.6,"lat":46.2473,"lon":4.7052,"fibre_pct":97.9,"securite":{"taux_pour_mille":9.1,"annee":2024},"socio":{"annee":2021,"revenu_median":23260.0},"vivrescore":80},{"code_insee":"69104","nom":"Jullié","codes_postaux":["69840"],"code_dep":"69","code_region":"84","population":492,"surface_km2":9.81,"lat":46.244,"lon":4.6632,"fibre_pct":94.0,"securite":{"taux_pour_mille":0.0,"annee":2024},"socio":{"annee":2021,"revenu_median":22170.0},"vivrescore":80},{"code_insee":"69105","nom":"Lacenas","codes_postaux":["69640"],"code_dep":"69","code_region":"84","population":1076,"surface_km2":3.33,"lat":45.9867,"lon":4.6447,"fibre_pct":97.0,"securite":{"taux_pour_mille":0.0,"annee":2024},"socio":{"annee":2021,"revenu_median":27670.0},"vivrescore":93},{"code_insee":"69106","nom":"Lachassagne","codes_postaux":["69480"],"code_dep":"69","code_region":"84","population":1332,"surface_km2":3.54,"lat":45.9264,"lon":4.6779,"fibre_pct":95.1,"securite":{"taux_pour_mille":7.5,"annee":2024},"socio":{"annee":2021,"revenu_median":32050.0},"vivrescore":93},{"code_insee":"69107","nom":"Lamure-sur-Azergues","codes_postaux":["69870"],"code_dep":"69","code_region":"84","population":1048,"surface_km2":15.52,"lat":46.053,"lon":4.5088,"fibre_pct":95.8,"securite":{"taux_pour_mille":21.9,"annee":2024},"socio":{"annee":2021,"revenu_median":23260.0},"vivrescore":73},{"code_insee":"69108","nom":"Lancié","codes_postaux":["69220"],"code_dep":"69","code_region":"84","population":1101,"surface_km2":6.59,"lat":46.1739,"lon":4.7295,"fibre_pct":96.9,"securite":{"taux_pour_mille":0.0,"annee":2024},"socio":{"annee":2021,"revenu_median":24230.0},"vivrescore":87},{"code_insee":"69109","nom":"Lantignié","codes_postaux":["69430"],"code_dep":"69","code_region":"84","population":849,"surface_km2":7.43,"lat":46.1584,"lon":4.6174,"fibre_pct":95.3,"securite":{"taux_pour_mille":5.9,"annee":2024},"socio":{"annee":2021,"revenu_median":24990.0},"vivrescore":80},{"code_insee":"69110","nom":"Larajasse","codes_postaux":["69590"],"code_dep":"69","code_region":"84","population":1804,"surface_km2":33.54,"lat":45.6073,"lon":4.5128,"fibre_pct":87.3,"securite":{"taux_pour_mille":3.8,"annee":2024},"socio":{"annee":2021,"revenu_median":22970.0},"vivrescore":80},{"code_insee":"69111","nom":"Légny","codes_postaux":["69620"],"code_dep":"69","code_region":"84","population":685,"surface_km2":4.08,"lat":45.905,"lon":4.5742,"fibre_pct":94.4,"securite":{"taux_pour_mille":0.0,"annee":2024},"socio":{"annee":2021,"revenu_median":26900.0},"vivrescore":87},{"code_insee":"69112","nom":"Lentilly","codes_postaux":["69210"],"code_dep":"69","code_region":"84","population":6623,"surface_km2":18.66,"lat":45.8166,"lon":4.6691,"fibre_pct":96.7,"securite":{"taux_pour_mille":36.8,"annee":2024},"socio":{"annee":2021,"revenu_median":29630.0,"taux_pauvrete":5.0},"vivrescore":73},{"code_insee":"69113","nom":"Létra","codes_postaux":["69620"],"code_dep":"69","code_region":"84","population":901,"surface_km2":14.7,"lat":45.9767,"lon":4.518,"fibre_pct":83.5,"securite":{"taux_pour_mille":0.0,"annee":2024},"socio":{"annee":2021,"revenu_median":24730.0},"vivrescore":80},{"code_insee":"69114","nom":"Porte des Pierres Dorées","codes_postaux":["69400","69640"],"code_dep":"69","code_region":"84","population":4185,"surface_km2":13.52,"lat":45.9628,"lon":4.6509,"fibre_pct":99.2,"securite":{"taux_pour_mille":15.4,"annee":2024},"socio":{"annee":2021,"revenu_median":27510.0},"vivrescore":80},{"code_insee":"69115","nom":"Limas","codes_postaux":["69400"],"code_dep":"69","code_region":"84","population":4750,"surface_km2":5.57,"lat":45.9717,"lon":4.7196,"fibre_pct":99.9,"securite":{"taux_pour_mille":50.1,"annee":2024},"socio":{"annee":2021,"revenu_median":24720.0,"taux_pauvrete":13.0},"vivrescore":60},{"code_insee":"69116","nom":"Limonest","codes_postaux":["69760"],"code_dep":"69","code_region":"84","population":4012,"surface_km2":9.1,"lat":45.8267,"lon":4.7682,"fibre_pct":99.0,"securite":{"taux_pour_mille":65.3,"annee":2024},"socio":{"annee":2021,"revenu_median":34510.0,"taux_pauvrete":7.0},"vivrescore":73},{"code_insee":"69117","nom":"Lissieu","codes_postaux":["69380"],"code_dep":"69","code_region":"84","population":3181,"surface_km2":5.74,"lat":45.8582,"lon":4.7496,"fibre_pct":95.9,"securite":{"taux_pour_mille":21.0,"annee":2024},"socio":{"annee":2021,"revenu_median":33180.0},"vivrescore":87},{"code_insee":"69118","nom":"Loire-sur-Rhône","codes_postaux":["69700"],"code_dep":"69","code_region":"84","population":2746,"surface_km2":16.51,"lat":45.5482,"lon":4.7847,"fibre_pct":97.3,"securite":{"taux_pour_mille":13.5,"annee":2024},"socio":{"annee":2021,"revenu_median":24520.0},"vivrescore":80},{"code_insee":"69119","nom":"Longes","codes_postaux":["69420"],"code_dep":"69","code_region":"84","population":938,"surface_km2":24.03,"lat":45.5083,"lon":4.6861,"fibre_pct":98.0,"securite":{"taux_pour_mille":0.0,"annee":2024},"socio":{"annee":2021,"revenu_median":23880.0},"vivrescore":87},{"code_insee":"69120","nom":"Longessaigne","codes_postaux":["69770"],"code_dep":"69","code_region":"84","population":589,"surface_km2":11.97,"lat":45.7833,"lon":4.4277,"fibre_pct":95.6,"securite":{"taux_pour_mille":0.0,"annee":2024},"socio":{"annee":2021,"revenu_median":23030.0},"vivrescore":87},{"code_insee":"69121","nom":"Lozanne","codes_postaux":["69380"],"code_dep":"69","code_region":"84","population":3182,"surface_km2":5.53,"lat":45.853,"lon":4.6846,"fibre_pct":99.5,"securite":{"taux_pour_mille":31.4,"annee":2024},"socio":{"annee":2021,"revenu_median":26930.0},"vivrescore":73},{"code_insee":"69122","nom":"Lucenay","codes_postaux":["69480"],"code_dep":"69","code_region":"84","population":2070,"surface_km2":6.47,"lat":45.9138,"lon":4.7095,"fibre_pct":97.9,"securite":{"taux_pour_mille":21.3,"annee":2024},"socio":{"annee":2021,"revenu_median":28690.0},"vivrescore":80},{"code_insee":"69123","nom":"Lyon","codes_postaux":["69001","69002","69003","69004","69005","69006","69007","69008","69009"],"code_dep":"69","code_region":"84","population":519127,"surface_km2":47.97,"lat":45.758,"lon":4.8351,"securite":{"taux_pour_mille":107.9,"annee":2024},"socio":{"annee":2021,"taux_pauvrete":16.0,"revenu_median":25430.0},"vivrescore":50},{"code_insee":"69124","nom":"Marchampt","codes_postaux":["69430"],"code_dep":"69","code_region":"84","population":450,"surface_km2":17.77,"lat":46.1086,"lon":4.5614,"fibre_pct":88.2,"securite":{"taux_pour_mille":0.0,"annee":2024},"socio":{"annee":2021,"revenu_median":21820.0},"vivrescore":80},{"code_insee":"69125","nom":"Marcilly-d'Azergues","codes_postaux":["69380"],"code_dep":"69","code_region":"84","population":1066,"surface_km2":4.24,"lat":45.8685,"lon":4.7301,"fibre_pct":95.4,"securite":{"taux_pour_mille":0.0,"annee":2024},"socio":{"annee":2021,"revenu_median":30530.0},"vivrescore":100},{"code_insee":"69126","nom":"Marcy","codes_postaux":["69480"],"code_dep":"69","code_region":"84","population":916,"surface_km2":3.34,"lat":45.9141,"lon":4.6755,"fibre_pct":100.0,"securite":{"taux_pour_mille":5.7,"annee":2024},"socio":{"annee":2021,"revenu_median":30160.0},"vivrescore":93},{"code_insee":"69127","nom":"Marcy-l'Étoile","codes_postaux":["69280"],"code_dep":"69","code_region":"84","population":3778,"surface_km2":5.37,"lat":45.7855,"lon":4.7129,"fibre_pct":98.6,"securite":{"taux_pour_mille":18.1,"annee":2024},"socio":{"annee":2021,"taux_pauvrete":7.0,"revenu_median":29680.0},"vivrescore":80},{"code_insee":"69130","nom":"Meaux-la-Montagne","codes_postaux":["69550"],"code_dep":"69","code_region":"84","population":223,"surface_km2":9.18,"lat":46.0444,"lon":4.4219,"fibre_pct":97.8,"securite":{"taux_pour_mille":0.0,"annee":2024},"socio":{"annee":2021,"revenu_median":24390.0},"vivrescore":87},{"code_insee":"69131","nom":"Messimy","codes_postaux":["69510"],"code_dep":"69","code_region":"84","population":3546,"surface_km2":11.1,"lat":45.6978,"lon":4.6748,"fibre_pct":96.1,"securite":{"taux_pour_mille":19.9,"annee":2024},"socio":{"annee":2021,"revenu_median":27280.0},"vivrescore":80},{"code_insee":"69132","nom":"Meys","codes_postaux":["69610"],"code_dep":"69","code_region":"84","population":861,"surface_km2":14.76,"lat":45.6813,"lon":4.4071,"fibre_pct":93.5,"securite":{"taux_pour_mille":8.2,"annee":2024},"socio":{"annee":2021,"revenu_median":22000.0},"vivrescore":73},{"code_insee":"69133","nom":"Millery","codes_postaux":["69390"],"code_dep":"69","code_region":"84","population":4299,"surface_km2":8.72,"lat":45.6307,"lon":4.781,"fibre_pct":97.7,"securite":{"taux_pour_mille":26.1,"annee":2024},"socio":{"annee":2021,"revenu_median":30670.0},"vivrescore":80},{"code_insee":"69134","nom":"Moiré","codes_postaux":["69620"],"code_dep":"69","code_region":"84","population":240,"surface_km2":2.04,"lat":45.9262,"lon":4.6034,"fibre_pct":100.0,"securite":{"taux_pour_mille":0.0,"annee":2024},"socio":{"annee":2021,"revenu_median":30920.0},"vivrescore":100},{"code_insee":"69135","nom":"Deux-Grosnes","codes_postaux":["69430","69860"],"code_dep":"69","code_region":"84","population":1946,"surface_km2":83.64,"lat":46.2379,"lon":4.5631,"fibre_pct":76.7,"securite":{"taux_pour_mille":12.0,"annee":2024},"socio":{"annee":2021,"revenu_median":21080.0},"vivrescore":67},{"code_insee":"69136","nom":"Montagny","codes_postaux":["69700"],"code_dep":"69","code_region":"84","population":3218,"surface_km2":8.22,"lat":45.6296,"lon":4.752,"fibre_pct":93.1,"securite":{"taux_pour_mille":22.7,"annee":2024},"socio":{"annee":2021,"revenu_median":27760.0},"vivrescore":73},{"code_insee":"69137","nom":"Montmelas-Saint-Sorlin","codes_postaux":["69640"],"code_dep":"69","code_region":"84","population":528,"surface_km2":4.2,"lat":46.0201,"lon":4.6035,"fibre_pct":100.0,"securite":{"taux_pour_mille":0.0,"annee":2024},"socio":{"annee":2021,"revenu_median":27240.0},"vivrescore":93},{"code_insee":"69138","nom":"Montromant","codes_postaux":["69610"],"code_dep":"69","code_region":"84","population":456,"surface_km2":11.13,"lat":45.7111,"lon":4.541,"fibre_pct":98.1,"securite":{"taux_pour_mille":0.0,"annee":2024},"socio":{"annee":2021,"revenu_median":22850.0},"vivrescore":87},{"code_insee":"69139","nom":"Montrottier","codes_postaux":["69770"],"code_dep":"69","code_region":"84","population":1400,"surface_km2":23.06,"lat":45.8014,"lon":4.4654,"fibre_pct":95.2,"securite":{"taux_pour_mille":0.0,"annee":2024},"socio":{"annee":2021,"revenu_median":23730.0},"vivrescore":87},{"code_insee":"69140","nom":"Morancé","codes_postaux":["69480"],"code_dep":"69","code_region":"84","population":2261,"surface_km2":9.29,"lat":45.8938,"lon":4.7016,"fibre_pct":95.7,"securite":{"taux_pour_mille":9.3,"annee":2024},"socio":{"annee":2021,"revenu_median":29600.0},"vivrescore":87},{"code_insee":"69141","nom":"Mornant","codes_postaux":["69440"],"code_dep":"69","code_region":"84","population":6282,"surface_km2":15.79,"lat":45.6162,"lon":4.6747,"fibre_pct":95.9,"securite":{"taux_pour_mille":37.2,"annee":2024},"socio":{"annee":2021,"revenu_median":27260.0,"taux_pauvrete":6.0},"vivrescore":73},{"code_insee":"69142","nom":"La Mulatière","codes_postaux":["69350"],"code_dep":"69","code_region":"84","population":6534,"surface_km2":1.84,"lat":45.7338,"lon":4.8118,"fibre_pct":94.0,"securite":{"taux_pour_mille":66.5,"annee":2024},"socio":{"annee":2021,"revenu_median":22750.0,"taux_pauvrete":19.0},"vivrescore":53},{"code_insee":"69143","nom":"Neuville-sur-Saône","codes_postaux":["69250"],"code_dep":"69","code_region":"84","population":7812,"surface_km2":5.45,"lat":45.8821,"lon":4.8404,"fibre_pct":96.7,"securite":{"taux_pour_mille":62.0,"annee":2024},"socio":{"annee":2021,"taux_pauvrete":15.0,"revenu_median":23150.0},"vivrescore":60},{"code_insee":"69145","nom":"Odenas","codes_postaux":["69460"],"code_dep":"69","code_region":"84","population":938,"surface_km2":9.08,"lat":46.0935,"lon":4.6417,"fibre_pct":99.8,"securite":{"taux_pour_mille":0.0,"annee":2024},"socio":{"annee":2021,"revenu_median":23900.0},"vivrescore":87},{"code_insee":"69148","nom":"Orliénas","codes_postaux":["69530"],"code_dep":"69","code_region":"84","population":2675,"surface_km2":10.4,"lat":45.6609,"lon":4.7207,"fibre_pct":99.0,"securite":{"taux_pour_mille":15.6,"annee":2024},"socio":{"annee":2021,"revenu_median":30280.0},"vivrescore":87},{"code_insee":"69149","nom":"Oullins-Pierre-Bénite","codes_postaux":["69310","69600"],"code_dep":"69","code_region":"84","population":38168,"surface_km2":8.85,"lat":45.708,"lon":4.8112,"fibre_pct":95.3,"securite":{"taux_pour_mille":54.6,"annee":2024},"socio":{"annee":2021,"revenu_median":23260.0,"taux_pauvrete":16.0},"vivrescore":60},{"code_insee":"69151","nom":"Le Perréon","codes_postaux":["69460"],"code_dep":"69","code_region":"84","population":1500,"surface_km2":14.51,"lat":46.0691,"lon":4.587,"fibre_pct":91.6,"securite":{"taux_pour_mille":4.0,"annee":2024},"socio":{"annee":2021,"revenu_median":24720.0},"vivrescore":80},{"code_insee":"69153","nom":"Poleymieux-au-Mont-d'Or","codes_postaux":["69250"],"code_dep":"69","code_region":"84","population":1412,"surface_km2":6.35,"lat":45.856,"lon":4.7927,"fibre_pct":99.6,"securite":{"taux_pour_mille":15.8,"annee":2024},"socio":{"annee":2021,"revenu_median":35970.0},"vivrescore":87},{"code_insee":"69154","nom":"Pollionnay","codes_postaux":["69290"],"code_dep":"69","code_region":"84","population":2958,"surface_km2":15.74,"lat":45.7707,"lon":4.6585,"fibre_pct":92.9,"securite":{"taux_pour_mille":13.1,"annee":2024},"socio":{"annee":2021,"revenu_median":28690.0},"vivrescore":80},{"code_insee":"69155","nom":"Pomeys","codes_postaux":["69590"],"code_dep":"69","code_region":"84","population":1126,"surface_km2":13.21,"lat":45.6466,"lon":4.4452,"fibre_pct":100.0,"securite":{"taux_pour_mille":0.0,"annee":2024},"socio":{"annee":2021,"revenu_median":25480.0},"vivrescore":93},{"code_insee":"69156","nom":"Pommiers","codes_postaux":["69480"],"code_dep":"69","code_region":"84","population":2618,"surface_km2":7.84,"lat":45.9581,"lon":4.6928,"fibre_pct":99.9,"securite":{"taux_pour_mille":34.2,"annee":2024},"socio":{"annee":2021,"revenu_median":30730.0},"vivrescore":80},{"code_insee":"69157","nom":"Vindry-sur-Turdine","codes_postaux":["69490"],"code_dep":"69","code_region":"84","population":5305,"surface_km2":23.77,"lat":45.8886,"lon":4.4948,"fibre_pct":94.8,"securite":{"taux_pour_mille":29.2,"annee":2024},"socio":{"annee":2021,"taux_pauvrete":6.0,"revenu_median":25190.0},"vivrescore":67},{"code_insee":"69160","nom":"Poule-les-Écharmeaux","codes_postaux":["69870"],"code_dep":"69","code_region":"84","population":1023,"surface_km2":31.28,"lat":46.1458,"lon":4.4698,"fibre_pct":92.2,"securite":{"taux_pour_mille":7.8,"annee":2024},"socio":{"annee":2021,"revenu_median":23210.0},"vivrescore":73},{"code_insee":"69161","nom":"Propières","codes_postaux":["69790"],"code_dep":"69","code_region":"84","population":484,"surface_km2":16.28,"lat":46.1909,"lon":4.4503,"fibre_pct":75.6,"securite":{"taux_pour_mille":0.0,"annee":2024},"socio":{"annee":2021,"revenu_median":20760.0},"vivrescore":73},{"code_insee":"69162","nom":"Quincié-en-Beaujolais","codes_postaux":["69430"],"code_dep":"69","code_region":"84","population":1408,"surface_km2":22.02,"lat":46.1118,"lon":4.614,"fibre_pct":98.6,"securite":{"taux_pour_mille":6.5,"annee":2024},"socio":{"annee":2021,"revenu_median":23660.0},"vivrescore":80},{"code_insee":"69163","nom":"Quincieux","codes_postaux":["69650"],"code_dep":"69","code_region":"84","population":3679,"surface_km2":17.98,"lat":45.9168,"lon":4.7724,"fibre_pct":94.7,"securite":{"taux_pour_mille":23.2,"annee":2024},"socio":{"annee":2021,"revenu_median":26670.0},"vivrescore":73},{"code_insee":"69164","nom":"Ranchal","codes_postaux":["69470"],"code_dep":"69","code_region":"84","population":304,"surface_km2":15.15,"lat":46.125,"lon":4.3974,"fibre_pct":98.5,"securite":{"taux_pour_mille":0.0,"annee":2024},"socio":{"annee":2021,"revenu_median":21590.0},"vivrescore":87},{"code_insee":"69165","nom":"Régnié-Durette","codes_postaux":["69430"],"code_dep":"69","code_region":"84","population":1151,"surface_km2":11.73,"lat":46.1531,"lon":4.6449,"fibre_pct":96.5,"securite":{"taux_pour_mille":4.3,"annee":2024},"socio":{"annee":2021,"revenu_median":24530.0},"vivrescore":87},{"code_insee":"69166","nom":"Riverie","codes_postaux":["69440"],"code_dep":"69","code_region":"84","population":293,"surface_km2":0.41,"lat":45.5985,"lon":4.5883,"fibre_pct":95.5,"securite":{"taux_pour_mille":0.0,"annee":2024},"socio":{"annee":2021,"revenu_median":25620.0},"vivrescore":93},{"code_insee":"69167","nom":"Rivolet","codes_postaux":["69640"],"code_dep":"69","code_region":"84","population":585,"surface_km2":16.14,"lat":46.0084,"lon":4.5829,"fibre_pct":97.2,"securite":{"taux_pour_mille":0.0,"annee":2024},"socio":{"annee":2021,"revenu_median":25220.0},"vivrescore":93},{"code_insee":"69168","nom":"Rochetaillée-sur-Saône","codes_postaux":["69270"],"code_dep":"69","code_region":"84","population":1551,"surface_km2":1.38,"lat":45.8427,"lon":4.8396,"fibre_pct":100.0,"securite":{"taux_pour_mille":41.4,"annee":2024},"socio":{"annee":2021,"revenu_median":29240.0},"vivrescore":67},{"code_insee":"69169","nom":"Ronno","codes_postaux":["69550"],"code_dep":"69","code_region":"84","population":658,"surface_km2":22.97,"lat":45.9845,"lon":4.3902,"fibre_pct":85.4,"securite":{"taux_pour_mille":0.0,"annee":2024},"socio":{"annee":2021,"revenu_median":23420.0},"vivrescore":80},{"code_insee":"69170","nom":"Rontalon","codes_postaux":["69510"],"code_dep":"69","code_region":"84","population":1170,"surface_km2":12.64,"lat":45.6554,"lon":4.6204,"fibre_pct":93.7,"securite":{"taux_pour_mille":6.0,"annee":2024},"socio":{"annee":2021,"revenu_median":25080.0},"vivrescore":80},{"code_insee":"69171","nom":"Sain-Bel","codes_postaux":["69210"],"code_dep":"69","code_region":"84","population":2566,"surface_km2":3.82,"lat":45.8115,"lon":4.6017,"fibre_pct":98.7,"securite":{"taux_pour_mille":31.5,"annee":2024},"socio":{"annee":2021,"revenu_median":24670.0,"taux_pauvrete":10.0},"vivrescore":67},{"code_insee":"69172","nom":"Salles-Arbuissonnas-en-Beaujolais","codes_postaux":["69460"],"code_dep":"69","code_region":"84","population":815,"surface_km2":4.37,"lat":46.0449,"lon":4.6317,"fibre_pct":97.8,"securite":{"taux_pour_mille":0.0,"annee":2024},"socio":{"annee":2021,"revenu_median":26240.0},"vivrescore":93},{"code_insee":"69173","nom":"Sarcey","codes_postaux":["69490"],"code_dep":"69","code_region":"84","population":980,"surface_km2":10.05,"lat":45.8839,"lon":4.5572,"fibre_pct":93.0,"securite":{"taux_pour_mille":18.4,"annee":2024},"socio":{"annee":2021,"revenu_median":27830.0},"vivrescore":73},{"code_insee":"69174","nom":"Les Sauvages","codes_postaux":["69170"],"code_dep":"69","code_region":"84","population":626,"surface_km2":12.52,"lat":45.9245,"lon":4.3695,"fibre_pct":86.1,"securite":{"taux_pour_mille":0.0,"annee":2024},"socio":{"annee":2021,"revenu_median":23270.0},"vivrescore":80},{"code_insee":"69175","nom":"Savigny","codes_postaux":["69210"],"code_dep":"69","code_region":"84","population":1995,"surface_km2":21.41,"lat":45.8174,"lon":4.5599,"fibre_pct":100.0,"securite":{"taux_pour_mille":13.2,"annee":2024},"socio":{"annee":2021,"revenu_median":26350.0},"vivrescore":87},{"code_insee":"69176","nom":"Soucieu-en-Jarrest","codes_postaux":["69510"],"code_dep":"69","code_region":"84","population":4660,"surface_km2":14.32,"lat":45.677,"lon":4.6907,"fibre_pct":95.9,"securite":{"taux_pour_mille":22.6,"annee":2024},"socio":{"annee":2021,"revenu_median":27650.0},"vivrescore":80},{"code_insee":"69177","nom":"Sourcieux-les-Mines","codes_postaux":["69210"],"code_dep":"69","code_region":"84","population":2100,"surface_km2":9.95,"lat":45.7979,"lon":4.6311,"fibre_pct":99.0,"securite":{"taux_pour_mille":7.1,"annee":2024},"socio":{"annee":2021,"revenu_median":28150.0},"vivrescore":87},{"code_insee":"69178","nom":"Souzy","codes_postaux":["69610"],"code_dep":"69","code_region":"84","population":763,"surface_km2":5.11,"lat":45.7027,"lon":4.4505,"fibre_pct":92.4,"securite":{"taux_pour_mille":0.0,"annee":2024},"socio":{"annee":2021,"revenu_median":22510.0},"vivrescore":80},{"code_insee":"69179","nom":"Beauvallon","codes_postaux":["69700"],"code_dep":"69","code_region":"84","population":4260,"surface_km2":24.61,"lat":45.5898,"lon":4.7041,"fibre_pct":95.5,"securite":{"taux_pour_mille":25.0,"annee":2024},"socio":{"annee":2021,"revenu_median":27940.0},"vivrescore":80},{"code_insee":"69180","nom":"Saint-André-la-Côte","codes_postaux":["69440"],"code_dep":"69","code_region":"84","population":269,"surface_km2":4.88,"lat":45.6313,"lon":4.5935,"fibre_pct":100.0,"securite":{"taux_pour_mille":0.0,"annee":2024},"socio":{"annee":2021,"revenu_median":25880.0},"vivrescore":93},{"code_insee":"69181","nom":"Saint-Appolinaire","codes_postaux":["69170"],"code_dep":"69","code_region":"84","population":236,"surface_km2":5.73,"lat":45.9772,"lon":4.4275,"fibre_pct":75.6,"securite":{"taux_pour_mille":0.0,"annee":2024},"socio":{"annee":2021,"revenu_median":23190.0},"vivrescore":73},{"code_insee":"69182","nom":"Saint-Bonnet-des-Bruyères","codes_postaux":["69790"],"code_dep":"69","code_region":"84","population":368,"surface_km2":21.26,"lat":46.2669,"lon":4.4721,"fibre_pct":79.9,"securite":{"taux_pour_mille":0.0,"annee":2024},"socio":{"annee":2021,"revenu_median":20380.0},"vivrescore":73},{"code_insee":"69183","nom":"Saint-Bonnet-le-Troncy","codes_postaux":["69870"],"code_dep":"69","code_region":"84","population":307,"surface_km2":15.5,"lat":46.0781,"lon":4.4172,"fibre_pct":86.1,"securite":{"taux_pour_mille":0.0,"annee":2024},"socio":{"annee":2021,"revenu_median":20390.0},"vivrescore":80},{"code_insee":"69184","nom":"Sainte-Catherine","codes_postaux":["69440"],"code_dep":"69","code_region":"84","population":969,"surface_km2":13.73,"lat":45.6036,"lon":4.5734,"fibre_pct":95.2,"securite":{"taux_pour_mille":0.0,"annee":2024},"socio":{"annee":2021,"revenu_median":25380.0},"vivrescore":93},{"code_insee":"69186","nom":"Saint-Clément-de-Vers","codes_postaux":["69790"],"code_dep":"69","code_region":"84","population":206,"surface_km2":8.94,"lat":46.2272,"lon":4.4157,"fibre_pct":81.7,"securite":{"taux_pour_mille":0.0,"annee":2024},"socio":{"annee":2021,"revenu_median":21850.0},"vivrescore":80},{"code_insee":"69187","nom":"Saint-Clément-les-Places","codes_postaux":["69930"],"code_dep":"69","code_region":"84","population":684,"surface_km2":12.41,"lat":45.7561,"lon":4.4207,"fibre_pct":94.9,"securite":{"taux_pour_mille":0.0,"annee":2024},"socio":{"annee":2021,"revenu_median":23090.0},"vivrescore":80},{"code_insee":"69188","nom":"Saint-Clément-sur-Valsonne","codes_postaux":["69170"],"code_dep":"69","code_region":"84","population":900,"surface_km2":14.58,"lat":45.926,"lon":4.4585,"fibre_pct":97.5,"securite":{"taux_pour_mille":0.0,"annee":2024},"socio":{"annee":2021,"revenu_median":23400.0},"vivrescore":87},{"code_insee":"69189","nom":"Sainte-Colombe","codes_postaux":["69560"],"code_dep":"69","code_region":"84","population":2036,"surface_km2":1.6,"lat":45.5247,"lon":4.8582,"fibre_pct":96.0,"securite":{"taux_pour_mille":25.6,"annee":2024},"socio":{"annee":2021,"taux_pauvrete":12.0,"revenu_median":24540.0},"vivrescore":67},{"code_insee":"69190","nom":"Sainte-Consorce","codes_postaux":["69280"],"code_dep":"69","code_region":"84","population":2154,"surface_km2":5.9,"lat":45.7765,"lon":4.6959,"fibre_pct":96.5,"securite":{"taux_pour_mille":14.2,"annee":2024},"socio":{"annee":2021,"revenu_median":30200.0},"vivrescore":93},{"code_insee":"69191","nom":"Saint-Cyr-au-Mont-d'Or","codes_postaux":["69450"],"code_dep":"69","code_region":"84","population":6327,"surface_km2":7.27,"lat":45.8216,"lon":4.8162,"fibre_pct":97.0,"securite":{"taux_pour_mille":48.4,"annee":2024},"socio":{"annee":2021,"revenu_median":40340.0,"taux_pauvrete":7.0},"vivrescore":73},{"code_insee":"69192","nom":"Saint-Cyr-le-Chatoux","codes_postaux":["69870"],"code_dep":"69","code_region":"84","population":154,"surface_km2":6.24,"lat":46.0335,"lon":4.5382,"fibre_pct":100.0,"securite":{"taux_pour_mille":0.0,"annee":2024},"socio":{"annee":2021,"revenu_median":25650.0},"vivrescore":93},{"code_insee":"69193","nom":"Saint-Cyr-sur-le-Rhône","codes_postaux":["69560"],"code_dep":"69","code_region":"84","population":1286,"surface_km2":6.06,"lat":45.5154,"lon":4.8242,"fibre_pct":99.8,"securite":{"taux_pour_mille":14.9,"annee":2024},"socio":{"annee":2021,"revenu_median":31000.0},"vivrescore":93},{"code_insee":"69194","nom":"Saint-Didier-au-Mont-d'Or","codes_postaux":["69370"],"code_dep":"69","code_region":"84","population":7435,"surface_km2":8.35,"lat":45.8159,"lon":4.8003,"fibre_pct":96.5,"securite":{"taux_pour_mille":32.1,"annee":2024},"socio":{"annee":2021,"taux_pauvrete":5.0,"revenu_median":42270.0},"vivrescore":80},{"code_insee":"69196","nom":"Saint-Didier-sur-Beaujeu","codes_postaux":["69430"],"code_dep":"69","code_region":"84","population":603,"surface_km2":14.53,"lat":46.1453,"lon":4.5341,"fibre_pct":92.8,"securite":{"taux_pour_mille":0.0,"annee":2024},"socio":{"annee":2021,"revenu_median":23770.0},"vivrescore":80},{"code_insee":"69197","nom":"Saint-Étienne-des-Oullières","codes_postaux":["69460"],"code_dep":"69","code_region":"84","population":2264,"surface_km2":9.66,"lat":46.0645,"lon":4.6557,"fibre_pct":99.3,"securite":{"taux_pour_mille":12.1,"annee":2024},"socio":{"annee":2021,"revenu_median":25040.0},"vivrescore":87},{"code_insee":"69198","nom":"Saint-Étienne-la-Varenne","codes_postaux":["69460"],"code_dep":"69","code_region":"84","population":784,"surface_km2":6.5,"lat":46.0765,"lon":4.6188,"fibre_pct":96.0,"securite":{"taux_pour_mille":0.0,"annee":2024},"socio":{"annee":2021,"revenu_median":25860.0},"vivrescore":93},{"code_insee":"69199","nom":"Saint-Fons","codes_postaux":["69190"],"code_dep":"69","code_region":"84","population":19285,"surface_km2":6.03,"lat":45.6997,"lon":4.8514,"fibre_pct":94.6,"securite":{"taux_pour_mille":62.4,"annee":2024},"socio":{"annee":2021,"taux_pauvrete":33.0,"revenu_median":16880.0},"vivrescore":47},{"code_insee":"69200","nom":"Saint-Forgeux","codes_postaux":["69490"],"code_dep":"69","code_region":"84","population":1544,"surface_km2":22.29,"lat":45.8522,"lon":4.4583,"fibre_pct":84.5,"securite":{"taux_pour_mille":8.5,"annee":2024},"socio":{"annee":2021,"revenu_median":24220.0},"vivrescore":73},{"code_insee":"69201","nom":"Sainte-Foy-l'Argentière","codes_postaux":["69610"],"code_dep":"69","code_region":"84","population":1312,"surface_km2":1.57,"lat":45.7044,"lon":4.4705,"fibre_pct":94.8,"securite":{"taux_pour_mille":9.3,"annee":2024},"socio":{"annee":2021,"revenu_median":20920.0},"vivrescore":73},{"code_insee":"69202","nom":"Sainte-Foy-lès-Lyon","codes_postaux":["69110"],"code_dep":"69","code_region":"84","population":21692,"surface_km2":6.84,"lat":45.7362,"lon":4.7926,"fibre_pct":95.8,"securite":{"taux_pour_mille":43.7,"annee":2024},"socio":{"annee":2021,"revenu_median":28780.0,"taux_pauvrete":9.0},"vivrescore":67},{"code_insee":"69203","nom":"Saint-Genis-l'Argentière","codes_postaux":["69610"],"code_dep":"69","code_region":"84","population":986,"surface_km2":10.9,"lat":45.7145,"lon":4.4926,"fibre_pct":95.6,"securite":{"taux_pour_mille":0.0,"annee":2024},"socio":{"annee":2021,"revenu_median":23380.0},"vivrescore":87},{"code_insee":"69204","nom":"Saint-Genis-Laval","codes_postaux":["69230"],"code_dep":"69","code_region":"84","population":21212,"surface_km2":12.91,"lat":45.6922,"lon":4.7929,"fibre_pct":96.6,"securite":{"taux_pour_mille":55.2,"annee":2024},"socio":{"annee":2021,"revenu_median":26810.0,"taux_pauvrete":10.0},"vivrescore":67},{"code_insee":"69205","nom":"Saint-Genis-les-Ollières","codes_postaux":["69290"],"code_dep":"69","code_region":"84","population":5439,"surface_km2":3.77,"lat":45.7614,"lon":4.7248,"fibre_pct":97.2,"securite":{"taux_pour_mille":30.9,"annee":2024},"socio":{"annee":2021,"revenu_median":30290.0,"taux_pauvrete":7.0},"vivrescore":80},{"code_insee":"69206","nom":"Saint-Georges-de-Reneins","codes_postaux":["69830"],"code_dep":"69","code_region":"84","population":4677,"surface_km2":27.38,"lat":46.0587,"lon":4.7164,"fibre_pct":94.5,"securite":{"taux_pour_mille":43.0,"annee":2024},"socio":{"annee":2021,"taux_pauvrete":7.0,"revenu_median":25200.0},"vivrescore":60},{"code_insee":"69207","nom":"Saint-Germain-au-Mont-d'Or","codes_postaux":["69650"],"code_dep":"69","code_region":"84","population":3124,"surface_km2":5.44,"lat":45.8842,"lon":4.8036,"fibre_pct":98.3,"securite":{"taux_pour_mille":42.8,"annee":2024},"socio":{"annee":2021,"taux_pauvrete":9.0,"revenu_median":27110.0},"vivrescore":67},{"code_insee":"69208","nom":"Saint-Germain-Nuelles","codes_postaux":["69210"],"code_dep":"69","code_region":"84","population":2246,"surface_km2":8.65,"lat":45.8604,"lon":4.6167,"fibre_pct":98.3,"securite":{"taux_pour_mille":14.2,"annee":2024},"socio":{"annee":2021,"revenu_median":28890.0},"vivrescore":87},{"code_insee":"69209","nom":"Saint-Igny-de-Vers","codes_postaux":["69790"],"code_dep":"69","code_region":"84","population":593,"surface_km2":27.21,"lat":46.2368,"lon":4.4381,"fibre_pct":72.9,"securite":{"taux_pour_mille":0.0,"annee":2024},"socio":{"annee":2021,"revenu_median":22390.0},"vivrescore":73},{"code_insee":"69212","nom":"Saint-Jean-des-Vignes","codes_postaux":["69380"],"code_dep":"69","code_region":"84","population":486,"surface_km2":2.59,"lat":45.8746,"lon":4.683,"fibre_pct":99.1,"securite":{"taux_pour_mille":0.0,"annee":2024},"socio":{"annee":2021,"revenu_median":30230.0},"vivrescore":100},{"code_insee":"69214","nom":"Saint-Jean-la-Bussière","codes_postaux":["69550"],"code_dep":"69","code_region":"84","population":1163,"surface_km2":15.64,"lat":46.0038,"lon":4.3341,"fibre_pct":81.0,"securite":{"taux_pour_mille":23.0,"annee":2024},"socio":{"annee":2021,"revenu_median":23570.0},"vivrescore":67},{"code_insee":"69215","nom":"Saint-Julien","codes_postaux":["69640"],"code_dep":"69","code_region":"84","population":969,"surface_km2":6.92,"lat":46.0252,"lon":4.648,"fibre_pct":98.7,"securite":{"taux_pour_mille":0.0,"annee":2024},"socio":{"annee":2021,"revenu_median":27530.0},"vivrescore":93},{"code_insee":"69216","nom":"Saint-Julien-sur-Bibost","codes_postaux":["69690"],"code_dep":"69","code_region":"84","population":622,"surface_km2":13.33,"lat":45.7984,"lon":4.5087,"fibre_pct":100.0,"securite":{"taux_pour_mille":0.0,"annee":2024},"socio":{"annee":2021,"revenu_median":23150.0},"vivrescore":87},{"code_insee":"69217","nom":"Saint-Just-d'Avray","codes_postaux":["69870"],"code_dep":"69","code_region":"84","population":741,"surface_km2":17.59,"lat":45.9994,"lon":4.4576,"fibre_pct":90.3,"securite":{"taux_pour_mille":0.0,"annee":2024},"socio":{"annee":2021,"revenu_median":23590.0},"vivrescore":80},{"code_insee":"69218","nom":"Saint-Lager","codes_postaux":["69220"],"code_dep":"69","code_region":"84","population":1056,"surface_km2":7.74,"lat":46.1129,"lon":4.6728,"fibre_pct":97.7,"securite":{"taux_pour_mille":0.0,"annee":2024},"socio":{"annee":2021,"revenu_median":24660.0},"vivrescore":87},{"code_insee":"69219","nom":"Saint-Laurent-d'Agny","codes_postaux":["69440"],"code_dep":"69","code_region":"84","population":2111,"surface_km2":10.65,"lat":45.6406,"lon":4.6828,"fibre_pct":97.9,"securite":{"taux_pour_mille":22.2,"annee":2024},"socio":{"annee":2021,"revenu_median":29190.0},"vivrescore":80},{"code_insee":"69220","nom":"Saint-Laurent-de-Chamousset","codes_postaux":["69930"],"code_dep":"69","code_region":"84","population":2017,"surface_km2":17.34,"lat":45.7402,"lon":4.4688,"fibre_pct":95.5,"securite":{"taux_pour_mille":17.9,"annee":2024},"socio":{"annee":2021,"revenu_median":24060.0},"vivrescore":73},{"code_insee":"69225","nom":"Saint-Marcel-l'Éclairé","codes_postaux":["69170"],"code_dep":"69","code_region":"84","population":575,"surface_km2":11.86,"lat":45.8712,"lon":4.4279,"fibre_pct":95.1,"securite":{"taux_pour_mille":0.0,"annee":2024},"socio":{"annee":2021,"revenu_median":24570.0},"vivrescore":87},{"code_insee":"69227","nom":"Saint-Martin-en-Haut","codes_postaux":["69850"],"code_dep":"69","code_region":"84","population":3942,"surface_km2":38.95,"lat":45.6583,"lon":4.5561,"fibre_pct":93.6,"securite":{"taux_pour_mille":25.8,"annee":2024},"socio":{"annee":2021,"taux_pauvrete":7.0,"revenu_median":24790.0},"vivrescore":60},{"code_insee":"69228","nom":"Chabanière","codes_postaux":["69440"],"code_dep":"69","code_region":"84","population":4323,"surface_km2":34.9,"lat":45.5853,"lon":4.6187,"fibre_pct":87.4,"securite":{"taux_pour_mille":32.8,"annee":2024},"socio":{"annee":2021,"revenu_median":25960.0,"taux_pauvrete":7.0},"vivrescore":67},{"code_insee":"69229","nom":"Saint-Nizier-d'Azergues","codes_postaux":["69870"],"code_dep":"69","code_region":"84","population":774,"surface_km2":24.19,"lat":46.083,"lon":4.4613,"fibre_pct":76.9,"securite":{"taux_pour_mille":11.6,"annee":2024},"socio":{"annee":2021,"revenu_median":22220.0},"vivrescore":67},{"code_insee":"69230","nom":"Sainte-Paule","codes_postaux":["69620"],"code_dep":"69","code_region":"84","population":338,"surface_km2":7.67,"lat":45.9722,"lon":4.5634,"fibre_pct":98.1,"securite":{"taux_pour_mille":0.0,"annee":2024},"socio":{"annee":2021,"revenu_median":24300.0},"vivrescore":87},{"code_insee":"69231","nom":"Saint-Pierre-la-Palud","codes_postaux":["69210"],"code_dep":"69","code_region":"84","population":2616,"surface_km2":7.54,"lat":45.7833,"lon":4.6163,"fibre_pct":98.0,"securite":{"taux_pour_mille":9.7,"annee":2024},"socio":{"annee":2021,"revenu_median":26870.0},"vivrescore":87},{"code_insee":"69233","nom":"Saint-Romain-au-Mont-d'Or","codes_postaux":["69270"],"code_dep":"69","code_region":"84","population":1247,"surface_km2":2.61,"lat":45.8355,"lon":4.8224,"fibre_pct":97.7,"securite":{"taux_pour_mille":16.1,"annee":2024},"socio":{"annee":2021,"revenu_median":35130.0},"vivrescore":87},{"code_insee":"69234","nom":"Saint-Romain-de-Popey","codes_postaux":["69490"],"code_dep":"69","code_region":"84","population":1725,"surface_km2":17.09,"lat":45.855,"lon":4.5291,"fibre_pct":92.8,"securite":{"taux_pour_mille":22.9,"annee":2024},"socio":{"annee":2021,"revenu_median":26410.0},"vivrescore":73},{"code_insee":"69235","nom":"Saint-Romain-en-Gal","codes_postaux":["69560"],"code_dep":"69","code_region":"84","population":2001,"surface_km2":13.65,"lat":45.5402,"lon":4.8307,"fibre_pct":89.2,"securite":{"taux_pour_mille":62.8,"annee":2024},"socio":{"annee":2021,"revenu_median":24390.0},"vivrescore":53},{"code_insee":"69236","nom":"Saint-Romain-en-Gier","codes_postaux":["69700"],"code_dep":"69","code_region":"84","population":600,"surface_km2":4.04,"lat":45.5637,"lon":4.7065,"fibre_pct":95.9,"securite":{"taux_pour_mille":0.0,"annee":2024},"socio":{"annee":2021,"revenu_median":24150.0},"vivrescore":87},{"code_insee":"69238","nom":"Saint-Symphorien-sur-Coise","codes_postaux":["69590"],"code_dep":"69","code_region":"84","population":3785,"surface_km2":4.07,"lat":45.6314,"lon":4.4456,"fibre_pct":93.1,"securite":{"taux_pour_mille":24.8,"annee":2024},"socio":{"annee":2021,"taux_pauvrete":12.0,"revenu_median":21800.0},"vivrescore":67},{"code_insee":"69239","nom":"Saint-Vérand","codes_postaux":["69620"],"code_dep":"69","code_region":"84","population":1164,"surface_km2":17.57,"lat":45.9234,"lon":4.5208,"fibre_pct":89.3,"securite":{"taux_pour_mille":4.4,"annee":2024},"socio":{"annee":2021,"revenu_median":25940.0},"vivrescore":87},{"code_insee":"69240","nom":"Saint-Vincent-de-Reins","codes_postaux":["69240"],"code_dep":"69","code_region":"84","population":635,"surface_km2":13.8,"lat":46.0715,"lon":4.3937,"fibre_pct":86.7,"securite":{"taux_pour_mille":0.0,"annee":2024},"socio":{"annee":2021,"revenu_median":21280.0},"vivrescore":80},{"code_insee":"69241","nom":"Taluyers","codes_postaux":["69440"],"code_dep":"69","code_region":"84","population":2686,"surface_km2":8.12,"lat":45.6343,"lon":4.7265,"fibre_pct":98.1,"securite":{"taux_pour_mille":13.5,"annee":2024},"socio":{"annee":2021,"revenu_median":28720.0},"vivrescore":87},{"code_insee":"69242","nom":"Taponas","codes_postaux":["69220"],"code_dep":"69","code_region":"84","population":914,"surface_km2":7.59,"lat":46.1238,"lon":4.7648,"fibre_pct":97.8,"securite":{"taux_pour_mille":117.8,"annee":2024},"socio":{"annee":2021,"revenu_median":23880.0},"vivrescore":60},{"code_insee":"69243","nom":"Tarare","codes_postaux":["69170"],"code_dep":"69","code_region":"84","population":10893,"surface_km2":14.1,"lat":45.9071,"lon":4.4302,"fibre_pct":94.5,"securite":{"taux_pour_mille":43.2,"annee":2024},"socio":{"annee":2021,"revenu_median":19730.0,"taux_pauvrete":21.0},"vivrescore":47},{"code_insee":"69244","nom":"Tassin-la-Demi-Lune","codes_postaux":["69160"],"code_dep":"69","code_region":"84","population":23200,"surface_km2":7.99,"lat":45.7637,"lon":4.7521,"fibre_pct":98.4,"securite":{"taux_pour_mille":53.1,"annee":2024},"socio":{"annee":2021,"taux_pauvrete":8.0,"revenu_median":29010.0},"vivrescore":67},{"code_insee":"69245","nom":"Ternand","codes_postaux":["69620"],"code_dep":"69","code_region":"84","population":762,"surface_km2":10.73,"lat":45.9508,"lon":4.5181,"fibre_pct":96.4,"securite":{"taux_pour_mille":0.0,"annee":2024},"socio":{"annee":2021,"revenu_median":25830.0},"vivrescore":93},{"code_insee":"69246","nom":"Theizé","codes_postaux":["69620"],"code_dep":"69","code_region":"84","population":1278,"surface_km2":11.9,"lat":45.9418,"lon":4.6277,"fibre_pct":100.0,"securite":{"taux_pour_mille":11.6,"annee":2024},"socio":{"annee":2021,"revenu_median":27890.0},"vivrescore":87},{"code_insee":"69248","nom":"Thizy-les-Bourgs","codes_postaux":["69240"],"code_dep":"69","code_region":"84","population":5771,"surface_km2":44.54,"lat":46.0505,"lon":4.3109,"fibre_pct":92.0,"securite":{"taux_pour_mille":33.1,"annee":2024},"socio":{"annee":2021,"revenu_median":21160.0,"taux_pauvrete":16.0},"vivrescore":60},{"code_insee":"69249","nom":"Thurins","codes_postaux":["69510"],"code_dep":"69","code_region":"84","population":3404,"surface_km2":19.34,"lat":45.6809,"lon":4.6252,"fibre_pct":91.3,"securite":{"taux_pour_mille":16.2,"annee":2024},"socio":{"annee":2021,"taux_pauvrete":6.0,"revenu_median":26100.0},"vivrescore":73},{"code_insee":"69250","nom":"La Tour-de-Salvagny","codes_postaux":["69890"],"code_dep":"69","code_region":"84","population":4649,"surface_km2":8.4,"lat":45.8086,"lon":4.7129,"fibre_pct":94.0,"securite":{"taux_pour_mille":85.9,"annee":2024},"socio":{"annee":2021,"revenu_median":33530.0},"vivrescore":67},{"code_insee":"69252","nom":"Trèves","codes_postaux":["69420"],"code_dep":"69","code_region":"84","population":712,"surface_km2":7.63,"lat":45.5358,"lon":4.6918,"fibre_pct":94.9,"securite":{"taux_pour_mille":0.0,"annee":2024},"socio":{"annee":2021,"revenu_median":25940.0},"vivrescore":87},{"code_insee":"69253","nom":"Tupin-et-Semons","codes_postaux":["69420"],"code_dep":"69","code_region":"84","population":653,"surface_km2":8.27,"lat":45.4941,"lon":4.7776,"fibre_pct":96.3,"securite":{"taux_pour_mille":0.0,"annee":2024},"socio":{"annee":2021,"revenu_median":27690.0},"vivrescore":93},{"code_insee":"69254","nom":"Valsonne","codes_postaux":["69170"],"code_dep":"69","code_region":"84","population":1005,"surface_km2":18.37,"lat":45.9463,"lon":4.4264,"fibre_pct":88.2,"securite":{"taux_pour_mille":0.0,"annee":2024},"socio":{"annee":2021,"revenu_median":22710.0},"vivrescore":80},{"code_insee":"69255","nom":"Vaugneray","codes_postaux":["69670"],"code_dep":"69","code_region":"84","population":6304,"surface_km2":25.15,"lat":45.73,"lon":4.6502,"fibre_pct":91.5,"securite":{"taux_pour_mille":20.7,"annee":2024},"socio":{"annee":2021,"taux_pauvrete":7.0,"revenu_median":26950.0},"vivrescore":73},{"code_insee":"69256","nom":"Vaulx-en-Velin","codes_postaux":["69120"],"code_dep":"69","code_region":"84","population":53069,"surface_km2":21.04,"lat":45.7776,"lon":4.925,"fibre_pct":97.7,"securite":{"taux_pour_mille":82.7,"annee":2024},"socio":{"annee":2021,"taux_pauvrete":33.0,"revenu_median":17180.0},"vivrescore":53},{"code_insee":"69257","nom":"Vaux-en-Beaujolais","codes_postaux":["69460"],"code_dep":"69","code_region":"84","population":1169,"surface_km2":17.7,"lat":46.0459,"lon":4.5801,"fibre_pct":96.9,"securite":{"taux_pour_mille":0.0,"annee":2024},"socio":{"annee":2021,"revenu_median":24940.0},"vivrescore":87},{"code_insee":"69258","nom":"Vauxrenard","codes_postaux":["69820"],"code_dep":"69","code_region":"84","population":311,"surface_km2":19.17,"lat":46.2207,"lon":4.6415,"fibre_pct":86.2,"securite":{"taux_pour_mille":0.0,"annee":2024},"socio":{"annee":2021,"revenu_median":23900.0},"vivrescore":80},{"code_insee":"69259","nom":"Vénissieux","codes_postaux":["69200"],"code_dep":"69","code_region":"84","population":65502,"surface_km2":15.45,"lat":45.7012,"lon":4.8805,"fibre_pct":84.6,"securite":{"taux_pour_mille":106.7,"annee":2024},"socio":{"annee":2021,"taux_pauvrete":34.0,"revenu_median":17140.0},"vivrescore":47},{"code_insee":"69260","nom":"Vernaison","codes_postaux":["69390"],"code_dep":"69","code_region":"84","population":5210,"surface_km2":4.21,"lat":45.6464,"lon":4.8121,"fibre_pct":98.5,"securite":{"taux_pour_mille":43.7,"annee":2024},"socio":{"annee":2021,"revenu_median":27760.0,"taux_pauvrete":12.0},"vivrescore":67},{"code_insee":"69261","nom":"Vernay","codes_postaux":["69430"],"code_dep":"69","code_region":"84","population":124,"surface_km2":5.55,"lat":46.1639,"lon":4.5279,"fibre_pct":69.4,"securite":{"taux_pour_mille":0.0,"annee":2024},"vivrescore":80},{"code_insee":"69263","nom":"Villechenève","codes_postaux":["69770"],"code_dep":"69","code_region":"84","population":922,"surface_km2":14.11,"lat":45.8144,"lon":4.4082,"fibre_pct":93.2,"securite":{"taux_pour_mille":0.0,"annee":2024},"socio":{"annee":2021,"revenu_median":22900.0},"vivrescore":80},{"code_insee":"69264","nom":"Villefranche-sur-Saône","codes_postaux":["69400"],"code_dep":"69","code_region":"84","population":36172,"surface_km2":9.37,"lat":45.9837,"lon":4.726,"fibre_pct":98.7,"securite":{"taux_pour_mille":72.2,"annee":2024},"socio":{"annee":2021,"taux_pauvrete":25.0,"revenu_median":19640.0},"vivrescore":53},{"code_insee":"69265","nom":"Ville-sur-Jarnioux","codes_postaux":["69640"],"code_dep":"69","code_region":"84","population":828,"surface_km2":10.29,"lat":45.9693,"lon":4.5942,"fibre_pct":98.6,"securite":{"taux_pour_mille":0.0,"annee":2024},"socio":{"annee":2021,"revenu_median":29320.0},"vivrescore":93},{"code_insee":"69266","nom":"Villeurbanne","codes_postaux":["69100"],"code_dep":"69","code_region":"84","population":163684,"surface_km2":14.9,"lat":45.7719,"lon":4.8898,"fibre_pct":93.3,"securite":{"taux_pour_mille":89.8,"annee":2024},"socio":{"annee":2021,"taux_pauvrete":21.0,"revenu_median":21540.0},"vivrescore":53},{"code_insee":"69267","nom":"Villié-Morgon","codes_postaux":["69910"],"code_dep":"69","code_region":"84","population":2148,"surface_km2":18.6,"lat":46.1612,"lon":4.6621,"fibre_pct":98.5,"securite":{"taux_pour_mille":18.8,"annee":2024},"socio":{"annee":2021,"revenu_median":24700.0},"vivrescore":73},{"code_insee":"69268","nom":"Vourles","codes_postaux":["69390"],"code_dep":"69","code_region":"84","population":3332,"surface_km2":5.6,"lat":45.6569,"lon":4.7691,"fibre_pct":99.7,"securite":{"taux_pour_mille":45.3,"annee":2024},"socio":{"annee":2021,"revenu_median":32340.0},"vivrescore":73},{"code_insee":"69269","nom":"Yzeron","codes_postaux":["69510"],"code_dep":"69","code_region":"84","population":995,"surface_km2":10.73,"lat":45.7115,"lon":4.6038,"fibre_pct":95.8,"securite":{"taux_pour_mille":32.7,"annee":2024},"socio":{"annee":2021,"revenu_median":25190.0},"vivrescore":73},{"code_insee":"69270","nom":"Chaponnay","codes_postaux":["69970"],"code_dep":"69","code_region":"84","population":4548,"surface_km2":18.91,"lat":45.6315,"lon":4.9584,"fibre_pct":96.8,"securite":{"taux_pour_mille":32.3,"annee":2024},"socio":{"annee":2021,"revenu_median":31360.0},"vivrescore":80},{"code_insee":"69271","nom":"Chassieu","codes_postaux":["69680"],"code_dep":"69","code_region":"84","population":11208,"surface_km2":11.58,"lat":45.7366,"lon":4.9638,"fibre_pct":98.7,"securite":{"taux_pour_mille":57.7,"annee":2024},"socio":{"annee":2021,"revenu_median":28750.0,"taux_pauvrete":8.0},"vivrescore":67},{"code_insee":"69272","nom":"Communay","codes_postaux":["69360"],"code_dep":"69","code_region":"84","population":4540,"surface_km2":10.49,"lat":45.5977,"lon":4.8359,"fibre_pct":96.3,"securite":{"taux_pour_mille":36.7,"annee":2024},"socio":{"annee":2021,"revenu_median":28770.0,"taux_pauvrete":6.0},"vivrescore":73},{"code_insee":"69273","nom":"Corbas","codes_postaux":["69960"],"code_dep":"69","code_region":"84","population":11315,"surface_km2":11.87,"lat":45.6654,"lon":4.9104,"fibre_pct":97.3,"securite":{"taux_pour_mille":77.3,"annee":2024},"socio":{"annee":2021,"revenu_median":25250.0,"taux_pauvrete":8.0},"vivrescore":67},{"code_insee":"69275","nom":"Décines-Charpieu","codes_postaux":["69150"],"code_dep":"69","code_region":"84","population":29877,"surface_km2":17.14,"lat":45.7759,"lon":4.9589,"fibre_pct":96.4,"securite":{"taux_pour_mille":55.0,"annee":2024},"socio":{"annee":2021,"revenu_median":22050.0,"taux_pauvrete":18.0},"vivrescore":60},{"code_insee":"69276","nom":"Feyzin","codes_postaux":["69320"],"code_dep":"69","code_region":"84","population":10304,"surface_km2":10.47,"lat":45.6736,"lon":4.8589,"fibre_pct":95.2,"securite":{"taux_pour_mille":54.1,"annee":2024},"socio":{"annee":2021,"taux_pauvrete":17.0,"revenu_median":22210.0},"vivrescore":60},{"code_insee":"69277","nom":"Genas","codes_postaux":["69740"],"code_dep":"69","code_region":"84","population":13421,"surface_km2":24.15,"lat":45.7286,"lon":5.0172,"fibre_pct":95.2,"securite":{"taux_pour_mille":47.8,"annee":2024},"socio":{"annee":2021,"revenu_median":30610.0,"taux_pauvrete":5.0},"vivrescore":73},{"code_insee":"69278","nom":"Genay","codes_postaux":["69730"],"code_dep":"69","code_region":"84","population":5585,"surface_km2":8.66,"lat":45.8989,"lon":4.8389,"fibre_pct":94.4,"securite":{"taux_pour_mille":42.8,"annee":2024},"socio":{"annee":2021,"revenu_median":26920.0,"taux_pauvrete":8.0},"vivrescore":60},{"code_insee":"69279","nom":"Jonage","codes_postaux":["69330"],"code_dep":"69","code_region":"84","population":6144,"surface_km2":12.09,"lat":45.7886,"lon":5.0377,"fibre_pct":97.5,"securite":{"taux_pour_mille":42.1,"annee":2024},"socio":{"annee":2021,"revenu_median":28030.0,"taux_pauvrete":5.0},"vivrescore":67},{"code_insee":"69280","nom":"Jons","codes_postaux":["69330"],"code_dep":"69","code_region":"84","population":1647,"surface_km2":7.3,"lat":45.7978,"lon":5.0798,"fibre_pct":97.8,"securite":{"taux_pour_mille":15.7,"annee":2024},"socio":{"annee":2021,"revenu_median":27110.0},"vivrescore":80},{"code_insee":"69281","nom":"Marennes","codes_postaux":["69970"],"code_dep":"69","code_region":"84","population":1992,"surface_km2":12.41,"lat":45.6248,"lon":4.9097,"fibre_pct":98.8,"securite":{"taux_pour_mille":20.2,"annee":2024},"socio":{"annee":2021,"revenu_median":29440.0},"vivrescore":80},{"code_insee":"69282","nom":"Meyzieu","codes_postaux":["69330"],"code_dep":"69","code_region":"84","population":36687,"surface_km2":23.45,"lat":45.7785,"lon":5.0114,"fibre_pct":98.1,"securite":{"taux_pour_mille":48.7,"annee":2024},"socio":{"annee":2021,"revenu_median":23860.0,"taux_pauvrete":13.0},"vivrescore":60},{"code_insee":"69283","nom":"Mions","codes_postaux":["69780"],"code_dep":"69","code_region":"84","population":13843,"surface_km2":11.66,"lat":45.6628,"lon":4.9467,"fibre_pct":99.1,"securite":{"taux_pour_mille":40.0,"annee":2024},"socio":{"annee":2021,"revenu_median":26070.0,"taux_pauvrete":9.0},"vivrescore":73},{"code_insee":"69284","nom":"Montanay","codes_postaux":["69250"],"code_dep":"69","code_region":"84","population":3308,"surface_km2":7.27,"lat":45.8793,"lon":4.8657,"fibre_pct":98.4,"securite":{"taux_pour_mille":22.0,"annee":2024},"socio":{"annee":2021,"revenu_median":33600.0},"vivrescore":87},{"code_insee":"69285","nom":"Pusignan","codes_postaux":["69330"],"code_dep":"69","code_region":"84","population":4119,"surface_km2":13.21,"lat":45.7571,"lon":5.0659,"fibre_pct":95.2,"securite":{"taux_pour_mille":70.4,"annee":2024},"socio":{"annee":2021,"revenu_median":27420.0,"taux_pauvrete":5.0},"vivrescore":67},{"code_insee":"69286","nom":"Rillieux-la-Pape","codes_postaux":["69140"],"code_dep":"69","code_region":"84","population":31389,"surface_km2":14.55,"lat":45.8265,"lon":4.895,"fibre_pct":96.4,"securite":{"taux_pour_mille":62.2,"annee":2024},"socio":{"annee":2021,"revenu_median":19980.0,"taux_pauvrete":25.0},"vivrescore":53},{"code_insee":"69287","nom":"Saint-Bonnet-de-Mure","codes_postaux":["69720"],"code_dep":"69","code_region":"84","population":6984,"surface_km2":16.61,"lat":45.6975,"lon":5.0241,"fibre_pct":96.6,"securite":{"taux_pour_mille":40.2,"annee":2024},"socio":{"annee":2021,"taux_pauvrete":5.0,"revenu_median":28700.0},"vivrescore":67},{"code_insee":"69288","nom":"Saint-Laurent-de-Mure","codes_postaux":["69720"],"code_dep":"69","code_region":"84","population":5791,"surface_km2":18.82,"lat":45.6842,"lon":5.0597,"fibre_pct":96.2,"securite":{"taux_pour_mille":49.7,"annee":2024},"socio":{"annee":2021,"revenu_median":27380.0,"taux_pauvrete":5.0},"vivrescore":67},{"code_insee":"69289","nom":"Saint-Pierre-de-Chandieu","codes_postaux":["69780"],"code_dep":"69","code_region":"84","population":4616,"surface_km2":29.32,"lat":45.6471,"lon":5.0085,"fibre_pct":95.6,"securite":{"taux_pour_mille":30.5,"annee":2024},"socio":{"annee":2021,"taux_pauvrete":5.0,"revenu_median":28430.0},"vivrescore":73},{"code_insee":"69290","nom":"Saint-Priest","codes_postaux":["69800"],"code_dep":"69","code_region":"84","population":49229,"surface_km2":29.72,"lat":45.7014,"lon":4.9474,"fibre_pct":97.9,"securite":{"taux_pour_mille":58.0,"annee":2024},"socio":{"annee":2021,"taux_pauvrete":19.0,"revenu_median":21420.0},"vivrescore":60},{"code_insee":"69291","nom":"Saint-Symphorien-d'Ozon","codes_postaux":["69360"],"code_dep":"69","code_region":"84","population":6186,"surface_km2":13.42,"lat":45.6386,"lon":4.8666,"fibre_pct":97.8,"securite":{"taux_pour_mille":39.8,"annee":2024},"socio":{"annee":2021,"revenu_median":26560.0,"taux_pauvrete":7.0},"vivrescore":73},{"code_insee":"69292","nom":"Sathonay-Camp","codes_postaux":["69580"],"code_dep":"69","code_region":"84","population":7019,"surface_km2":1.92,"lat":45.8255,"lon":4.8792,"fibre_pct":99.0,"securite":{"taux_pour_mille":42.1,"annee":2024},"socio":{"annee":2021,"revenu_median":24460.0,"taux_pauvrete":11.0},"vivrescore":60},{"code_insee":"69293","nom":"Sathonay-Village","codes_postaux":["69580"],"code_dep":"69","code_region":"84","population":2412,"surface_km2":5.11,"lat":45.8394,"lon":4.8858,"fibre_pct":99.6,"securite":{"taux_pour_mille":17.4,"annee":2024},"socio":{"annee":2021,"revenu_median":33220.0},"vivrescore":87},{"code_insee":"69294","nom":"Sérézin-du-Rhône","codes_postaux":["69360"],"code_dep":"69","code_region":"84","population":3133,"surface_km2":3.84,"lat":45.6285,"lon":4.8248,"fibre_pct":93.9,"securite":{"taux_pour_mille":33.4,"annee":2024},"socio":{"annee":2021,"revenu_median":26360.0},"vivrescore":67},{"code_insee":"69295","nom":"Simandres","codes_postaux":["69360"],"code_dep":"69","code_region":"84","population":1918,"surface_km2":9.45,"lat":45.6111,"lon":4.8718,"fibre_pct":98.3,"securite":{"taux_pour_mille":22.8,"annee":2024},"socio":{"annee":2021,"revenu_median":28190.0},"vivrescore":80},{"code_insee":"69296","nom":"Solaize","codes_postaux":["69360"],"code_dep":"69","code_region":"84","population":3144,"surface_km2":8.13,"lat":45.6462,"lon":4.8331,"fibre_pct":97.1,"securite":{"taux_pour_mille":57.2,"annee":2024},"socio":{"annee":2021,"revenu_median":29430.0},"vivrescore":67},{"code_insee":"69297","nom":"Ternay","codes_postaux":["69360"],"code_dep":"69","code_region":"84","population":5596,"surface_km2":7.92,"lat":45.6083,"lon":4.803,"fibre_pct":95.8,"securite":{"taux_pour_mille":31.9,"annee":2024},"socio":{"annee":2021,"taux_pauvrete":8.0,"revenu_median":27400.0},"vivrescore":73},{"code_insee":"69298","nom":"Toussieu","codes_postaux":["69780"],"code_dep":"69","code_region":"84","population":3177,"surface_km2":5.07,"lat":45.6585,"lon":4.9819,"fibre_pct":92.8,"securite":{"taux_pour_mille":20.4,"annee":2024},"socio":{"annee":2021,"revenu_median":29590.0},"vivrescore":73},{"code_insee":"69299","nom":"Colombier-Saugnieu","codes_postaux":["69124","69125"],"code_dep":"69","code_region":"84","population":2874,"surface_km2":27.84,"lat":45.7174,"lon":5.1084,"fibre_pct":95.3,"securite":{"taux_pour_mille":249.4,"annee":2024},"socio":{"annee":2021,"revenu_median":27000.0},"vivrescore":67}]